Workbook
Name __CCD30: [1]Datos!$W$5:$W$28
Name __CCD60: [1]Datos!$X$5:$X$28
Name __CCD90: [1]Datos!$Y$5:$Y$28
Name __CCT30: [1]Datos!$S$5:$S$28
Name __CCT60: [1]Datos!$T$5:$T$28
Name __CCT90: [1]Datos!$U$5:$U$28
Name __CPD30: [1]Datos!$AE$5:$AE$28
Name __CPD60: [1]Datos!$AF$5:$AF$28
Name __CPD90: [1]Datos!$AG$5:$AG$28
Name __CPT30: [1]Datos!$AA$5:$AA$28
Name __CPT60: [1]Datos!$AB$5:$AB$28
Name __CPT90: [1]Datos!$AC$5:$AC$28
Name _CCD30: [1]Datos!$W$5:$W$28
Name _CCD60: [1]Datos!$X$5:$X$28
Name _CCD90: [1]Datos!$Y$5:$Y$28
Name _CCT30: [1]Datos!$S$5:$S$28
Name _CCT60: [1]Datos!$T$5:$T$28
Name _CCT90: [1]Datos!$U$5:$U$28
Name _CPD30: [1]Datos!$AE$5:$AE$28
Name _CPD60: [1]Datos!$AF$5:$AF$28
Name _CPD90: [1]Datos!$AG$5:$AG$28
Name _CPT30: [1]Datos!$AA$5:$AA$28
Name _CPT60: [1]Datos!$AB$5:$AB$28
Name _CPT90: [1]Datos!$AC$5:$AC$28
Name _m1: [1]Datos!$S$5:$S$28
Name _o1: [1]Datos!$V$5:$V$28
Name _r: [1]Datos!$X$5:$X$28
Name _y1: [1]Datos!$Y$5:$Y$28
Name B_Pre: [2]!PB
Name B_Pre: [3]!PB
Name balance_type: 1
Name BM_1: [4]!b_1
Name BM_1: [5]!b_1
Name BM_1b: [4]!b_1b
Name BM_1b: [5]!b_1b
Name BM_2: [4]!b_2
Name BM_2: [5]!b_2
Name BM_3: [4]!b_3
Name BM_3: [5]!b_3
Name BM_6: [4]!b_6
Name BM_6: [5]!b_6
Name BM_7: [4]!b_7
Name BM_7: [5]!b_7
Name BM_8: [4]!b_8
Name BM_8: [5]!b_8
Name calc: 1
Name CCDT: [1]Datos!$V$5:$V$28
Name CCTT: [1]Datos!$R$5:$R$28
Name co: 951
Name CPDT: [1]Datos!$AD$5:$AD$28
Name CPTT: [1]Datos!$Z$5:$Z$28
Name Criterio: [1]Datos!$E$5:$E$28
Name CUBAGOLF: #REF!
Name FY: 1999
Name LILI: #REF!
Name MESES: #REF!
Name MESES: #REF!
Name MESES: #REF!
Name NOMES: #REF!
Name NOMES: #REF!

Sheet Hoja1
B2: OSDE o Empresa: CAMPISMO POPULAR
B3: UM: Miles de CUP
B4: INDICADORES | C4: ESTIMADO DE CIERRE AÑO ACTUAL | D4: MODELACION | E4: Propuesta 2 | F4: Variación Absoluta
C5: 1 | D5: 2 | E5: 2 | F5: 2 - 1
B6: Ingresos Totales | C6: ='EMPLEO Y SALARIO'!D23 -> 1966778.8 | D6: 2164662.3 | E6: 2164662.3 | F6: =D6-C6 -> 197883.47 | H6: Incremento Gastos Asociados al Salario | L6: =D7*0.5 -> 975300 | M6: =L6*1.05 -> 1024065 | N6: =D6-D7 -> 214062.3
B7: VENTAS NETAS | C7: 1889000 | D7: 1950600 | E7: 2096895 | F7: =D7-C7 -> 61600 | G7: Impuesto salario | J7: =D7/C7 -> 1.0326098 | L7: =D7*0.05 -> 97530 | M7: =L7*2 -> 195060
B8: COSTOS Y GASTOS | C8: =C6-C11 -> 1809770.2 | D8: 2078242 | E8: 2078242 | F8: =D8-C8 -> 268471.75 | L8: =SUM(L6:L7) -> 1072830 | M8: =SUM(M6:M7) -> 1219125
B9: FONDO DE SALARIO | C9: ='EMPLEO Y SALARIO'!M23 -> 149208.96 | D9: ='P 14-B'!T48+'P 14-B'!T49 -> 230375.08 | E9: 323931.44 | F9: =D9-C9 -> 81166.124 | G9: =F9*19% -> 15421.564 | H9: =SUM(F9:G9) -> 96587.687 | J9: =D9/C9 -> 1.5439762 | L9: =D7-L8 -> 877770
B10: MONTO DE ESTIM EN DIVISAS A 1 USD X 120 CUP | C10: 0 | D10: ='P 14-B'!T50 -> 60595.2 | E10: 60552 | F10: =D10-C10 -> 60595.2 | H10: =H9+F10 -> 157182.89 | M10: =M8+L9 -> 2096895 | N10: =M10+N6 -> 2310957.3
B11: UTILIDAD A/IMP. | C11: ='EMPLEO Y SALARIO'!J23 -> 157008.62 | D11: =D6-D8 -> 86420.338 | E11: =E6-E8 -> 86420.338 | F11: =D11-C11 -> -70588.28 | G11: =E11/C11 -> 0.5504178 | H11: =C8+H10 -> 1966953.1
B12: PROMEDIO DE TRABAJADORES | C12: ='EMPLEO Y SALARIO'!P23 -> 4205 | D12: ='P 14-B'!T35 -> 4208 | E12: 4205 | F12: =D12-C12 -> 3
B13: A - SALARIO MEDIO | C13: =C9/C12/12*1000 -> 2956.975 | D13: =D9/D12/12*1000 -> 4562.2442 | E13: =E9/E12/12*1000 -> 6419.5687 | F13: =D13-C13 -> 1605.2692 | G13: =D13/C13 -> 1.5428755
B14: B - ESTIM EN DIVISAS PROM (1200 PESOS MENSUAL) | C14: =C10/C12/12 -> 0 | D14: =D10/D12/12 -> 1.2 | E14: =E10/E12/12 -> 1.2 | F14: =D14-C14 -> 1.2
B15: C - DIST. UTILIDADES PROM POR TRABAJADOR | C15: =C11/C12/12*100 -> 311.15461 | D15: =D11/D12/12*100 -> 171.14294 | E15: =E11/E12/12*100 -> 171.26504 | F15: =D15-C15 -> -140.01168 | I15: Propuesta 2 significa
B16: D - TOTAL DE INGRESO MEDIO MENSUAL | C16: =C13+C15 -> 3268.1296 | D16: =D13+D15 -> 4733.3871 | E16: =E13+E15 -> 6590.8338 | F16: =D16-C16 -> 1465.2575 | I16: 1- incremento del componente salario en las fichas de precios de los servicios gastronomicos que es un 5% por encima del actual
I17: 2- duplicar el precio del alojamiento en moneda nacional actual
B18: CANT INSTALACIONES QUE CIERRAN EN PERDIDA
B19: DE ELLAS - PROM TRABAJADORES IMPLICADOS
B20: % de Salario / Ventas Netas | C20: =C9/C7*100 -> 7.8988332 | D20: =D9/D7*100 -> 11.810473 | E20: =E9/E7*100 -> 15.448148 | F20: =D20-C20 -> 3.9116396
B21: % Estimulacion / Ventas Netas | C21: =C10/C7*100 -> 0 | D21: =D10/D7*100 -> 3.1064903 | E21: =E10/E7*100 -> 2.8876982 | F21: =D21-C21 -> 3.1064903
B23: NOTA:
B24: A = FONDO DE SALARIO ENTRE PROM TRABAJADORES ENTRE 12 MESES
B25: B = FONDO DE SALARIO ENTRE PROM TRABAJADORES ENTRE 12 MESES
B26: C = DISTRIBUCION DE UTILIDADES ENTRE PROM TRABAJADORES ENTRE 12 MESES
B27: D = A + B

Sheet EMPLEO Y SALARIO
A2: GRUPO EMPRESARIAL CAMPISMO POPULAR
A3: INDICADORES EMPLEO Y SALARIO (MT)
A4: ACUMULADO HASTA: | K4: =[7]VENTAS!G4 -> Junio 2025
A5: EMPRESAS | B5: Ingresos Totales | E5: VALOR AGREGADO | H5: UTILIDAD | K5: FONDO SALARIO | N5: PROMEDIO TRABAJADORES
B6: II Sem 2024 | C6: I Sem 2025 | D6: 2025 | E6: II Sem 2024 | F6: I Sem 2025 | G6: 2025 | H6: II Sem 2024 | I6: I Sem 2025 | J6: 2025 | K6: II Sem 2024 | L6: I Sem 2025 | M6: 2025 | N6: II Sem 2024 | O6: I Sem 2025 | P6: 2025
A7: Pinar del Río | B7: 48210.8 | C7: 89157.88 | D7: =SUM(B7:C7) -> 137368.68 | E7: 14772.46 | F7: =[7]PR!K5 -> 32325.66 | G7: =SUM(E7:F7) -> 47098.12 | H7: -582.38 | I7: =[7]RESULTADO!M7 -> 16163.36 | J7: =SUM(H7:I7) -> 15580.98 | K7: 8263.03 | L7: ='[7]PR B'!K30 -> 4957.56 | M7: =SUM(K7:L7) -> 13220.59 | N7: 366 | O7: 366 | P7: =SUM(N7:O7)/2 -> 366
A8: Artemisa | B8: 160308.04 | C8: 104685.92 | D8: =SUM(B8:C8) -> 264993.96 | E8: 33368.26 | F8: =[7]ART!K5 -> 23280.16 | G8: =SUM(E8:F8) -> 56648.42 | H8: 6170.11 | I8: =[7]RESULTADO!M8 -> 2513.35 | J8: =SUM(H8:I8) -> 8683.46 | K8: 6496.49 | L8: ='[7]ART B '!K30 -> 5962.61 | M8: =SUM(K8:L8) -> 12459.1 | N8: 375 | O8: 375 | P8: =SUM(N8:O8)/2 -> 375
A9: Casa Matriz | B9: =42217.86-21618.71 -> 20599.15 | C9: 16945.77 | D9: =SUM(B9:C9) -> 37544.92 | E9: 642.24 | F9: =[7]OC!K5 -> 1463.71 | G9: =SUM(E9:F9) -> 2105.95 | H9: -570.55 | I9: =[7]RESULTADO!M10 -> 0 | J9: =SUM(H9:I9) -> -570.55 | K9: 1000.16 | L9: ='[7]OC B'!K30 -> 1082.72 | M9: =SUM(K9:L9) -> 2082.88 | N9: 48 | O9: 35 | P9: =SUM(N9:O9)/2 -> 41.5
A10: HABANA | B10: 175702.67 | C10: 111410.94 | D10: =SUM(B10:C10) -> 287113.61 | E10: 35256.37 | F10: =[7]HAB!K5 -> 37554.97 | G10: =SUM(E10:F10) -> 72811.34 | H10: 11913.99 | I10: =[7]RESULTADO!M9 -> 14020.67 | J10: =SUM(H10:I10) -> 25934.66 | K10: 8213.12 | L10: ='[7]HAB B'!K30 -> 7884.9 | M10: =SUM(K10:L10) -> 16098.02 | N10: 226 | O10: 226 | P10: =SUM(N10:O10)/2 -> 226
A11: MAYABEQUE | B11: 50392.86 | C11: 60917.19 | D11: =SUM(B11:C11) -> 111310.05 | E11: 16372.06 | F11: =[7]MAY!K5 -> 16289.95 | G11: =SUM(E11:F11) -> 32662.01 | H11: 5044.11 | I11: =[7]RESULTADO!M11 -> 4897.57 | J11: =SUM(H11:I11) -> 9941.68 | K11: 4955.01 | L11: ='[7]MAY B'!K30 -> 4030.59 | M11: =SUM(K11:L11) -> 8985.6 | N11: 520 | O11: 365 | P11: =SUM(N11:O11)/2 -> 442.5
A12: Matanzas | B12: 60167.58 | C12: 76402.51 | D12: =SUM(B12:C12) -> 136570.09 | E12: 15976.333 | F12: =[7]MAT!K5 -> 23795.12 | G12: =SUM(E12:F12) -> 39771.453 | H12: 6208.8326 | I12: =[7]RESULTADO!M12 -> 12648.47 | J12: =SUM(H12:I12) -> 18857.303 | K12: 3366.89 | L12: ='[7]MAT B'!K30 -> 3687.79 | M12: =SUM(K12:L12) -> 7054.68 | N12: 152 | O12: 152 | P12: =SUM(N12:O12)/2 -> 152
A13: Villa Clara | B13: 25158.48 | C13: 25434.21 | D13: =SUM(B13:C13) -> 50592.69 | E13: 9549.5519 | F13: =[7]VC!K5 -> 9397.64 | G13: =SUM(E13:F13) -> 18947.192 | H13: 601.71192 | I13: =[7]RESULTADO!M13 -> 21.38 | J13: =SUM(H13:I13) -> 623.09192 | K13: 4690.73 | L13: ='[7]VC B'!K30 -> 4853.17 | M13: =SUM(K13:L13) -> 9543.9 | N13: 312 | O13: 312 | P13: =SUM(N13:O13)/2 -> 312
A14: Cienfuegos | B14: 50694.85 | C14: 62463.8 | D14: =SUM(B14:C14) -> 113158.65 | E14: 13804.49 | F14: =[7]CFG!K5 -> 15834.94 | G14: =SUM(E14:F14) -> 29639.43 | H14: 5310.36 | I14: =[7]RESULTADO!M14 -> 5677.42 | J14: =SUM(H14:I14) -> 10987.78 | K14: 4230.03 | L14: ='[7]CFG B'!K30 -> 4825.82 | M14: =SUM(K14:L14) -> 9055.85 | N14: 209 | O14: 209 | P14: =SUM(N14:O14)/2 -> 209
A15: Sancti Spíritus | B15: 48628.59 | C15: 46522.87 | D15: =SUM(B15:C15) -> 95151.46 | E15: 8262.48 | F15: =[7]SSP!K5 -> 11149.63 | G15: =SUM(E15:F15) -> 19412.11 | H15: -1842.32 | I15: =[7]RESULTADO!M15 -> 1598.9 | J15: =SUM(H15:I15) -> -243.42 | K15: 3675.63 | L15: ='[7]SSP B'!K30 -> 3304.66 | M15: =SUM(K15:L15) -> 6980.29 | N15: 144 | O15: 224 | P15: =SUM(N15:O15)/2 -> 184
A16: Ciego de Avila | B16: 23130.36 | C16: 20418.81 | D16: =SUM(B16:C16) -> 43549.17 | E16: 8420.27 | F16: =[7]CAV!K5 -> 7584.01 | G16: =SUM(E16:F16) -> 16004.28 | H16: 2604.31 | I16: =[7]RESULTADO!M16 -> 1636.49 | J16: =SUM(H16:I16) -> 4240.8 | K16: 2671.18 | L16: ='[7]CAV B'!K30 -> 3178.18 | M16: =SUM(K16:L16) -> 5849.36 | N16: 381 | O16: 201 | P16: =SUM(N16:O16)/2 -> 291
A17: Camagüey | B17: 96675.22 | C17: 113972.73 | D17: =SUM(B17:C17) -> 210647.95 | E17: 25400.115 | F17: =[7]CMG!K5 -> 29644.97 | G17: =SUM(E17:F17) -> 55045.085 | H17: 8547.6253 | I17: =[7]RESULTADO!M17 -> 11395.17 | J17: =SUM(H17:I17) -> 19942.795 | K17: 4914.46 | L17: ='[7]CMG B'!K30 -> 4258.48 | M17: =SUM(K17:L17) -> 9172.94 | N17: 258 | O17: 358 | P17: =SUM(N17:O17)/2 -> 308
A18: Las Tunas | B18: 22965.95 | C18: 22884.53 | D18: =SUM(B18:C18) -> 45850.48 | E18: 8768.3678 | F18: =[7]LT!K5 -> 7572.36 | G18: =SUM(E18:F18) -> 16340.728 | H18: 1743.2178 | I18: =[7]RESULTADO!M18 -> 385.05 | J18: =SUM(H18:I18) -> 2128.2678 | K18: 3644.37 | L18: ='[7]LT B'!K30 -> 3081.3 | M18: =SUM(K18:L18) -> 6725.67 | N18: 227 | O18: 227 | P18: =SUM(N18:O18)/2 -> 227
A19: Holguín | B19: 82309.12 | C19: 123511.52 | D19: =SUM(B19:C19) -> 205820.64 | E19: 24088.61 | F19: =[7]HLG!K5 -> 38509.45 | G19: =SUM(E19:F19) -> 62598.06 | H19: 3985.45 | I19: =[7]RESULTADO!M19 -> 10213.43 | J19: =SUM(H19:I19) -> 14198.88 | K19: 8570.84 | L19: ='[7]HLG B'!K30 -> 11651.85 | M19: =SUM(K19:L19) -> 20222.69 | N19: 471 | O19: 471 | P19: =SUM(N19:O19)/2 -> 471
A20: Granma | B20: 45066.59 | C20: 42066.16 | D20: =SUM(B20:C20) -> 87132.75 | E20: 17339.93 | F20: =[7]GRM!K5 -> 15876.21 | G20: =SUM(E20:F20) -> 33216.14 | H20: 8778.62 | I20: =[7]RESULTADO!M20 -> 6348.46 | J20: =SUM(H20:I20) -> 15127.08 | K20: 2713.45 | L20: ='[7]GRM B'!K30 -> 3685.09 | M20: =SUM(K20:L20) -> 6398.54 | N20: 193 | O20: 193 | P20: =SUM(N20:O20)/2 -> 193
A21: Stgo Cuba | B21: 57541.85 | C21: 35116.07 | D21: =SUM(B21:C21) -> 92657.92 | E21: 19788.69 | F21: =[7]SC!K5 -> 11124.99 | G21: =SUM(E21:F21) -> 30913.68 | H21: 8237.43 | I21: =[7]RESULTADO!M21 -> 2200.79 | J21: =SUM(H21:I21) -> 10438.22 | K21: 4321.27 | L21: ='[7]SC B'!K30 -> 3829.86 | M21: =SUM(K21:L21) -> 8151.13 | N21: 220 | O21: 220 | P21: =SUM(N21:O21)/2 -> 220
A22: Guantanamo | B22: 26017.86 | C22: 21297.95 | D22: =SUM(B22:C22) -> 47315.81 | E22: 7814.41 | F22: =[7]GTM!K5 -> 6401.74 | G22: =SUM(E22:F22) -> 14216.15 | H22: 737.5 | I22: =[7]RESULTADO!M22 -> 400.09 | J22: =SUM(H22:I22) -> 1137.59 | K22: 3882.15 | L22: ='[7]GTM B'!K30 -> 3325.57 | M22: =SUM(K22:L22) -> 7207.72 | N22: 187 | O22: 187 | P22: =SUM(N22:O22)/2 -> 187
A23: TOTAL | B23: =SUM(B7:B22) -> 993569.97 | C23: =SUM(C7:C22) -> 973208.86 | D23: =SUM(B23:C23) -> 1966778.8 | E23: =SUM(E7:E22) -> 259624.64 | F23: =SUM(F7:F22) -> 287805.51 | G23: =SUM(E23:F23) -> 547430.15 | H23: =SUM(H7:H22) -> 66888.018 | I23: =SUM(I7:I22) -> 90120.6 | J23: =SUM(H23:I23) -> 157008.62 | K23: =SUM(K7:K22) -> 75608.81 | L23: =SUM(L7:L22) -> 73600.15 | M23: =SUM(K23:L23) -> 149208.96 | N23: =SUM(N7:N22) -> 4289 | O23: =SUM(O7:O22) -> 4121 | P23: =SUM(N23:O23)/2 -> 4205 | Q23: =C24-C23 -> 218244.58
B24: II Sem 2025 | C24: =Hoja1!D6-'EMPLEO Y SALARIO'!C23 -> 1191453.4
A25: EMPRESAS | B25: Ventas Netas | E25: GS/VAB | H25: SALARIO MEDIO | K25: PRODUCTIVIDAD | N25: COR. SAL. MED./PRODUCTIVIDAD
B26: II Sem 2024 | C26: I Sem 2025 | D26: 2025 | E26: II Sem 2024 | F26: I Sem 2025 | G26: 2025 | H26: II Sem 2024 | I26: I Sem 2025 | J26: 2025 | K26: II Sem 2024 | L26: I Sem 2025 | M26: 2025 | N26: II Sem 2024 | O26: I Sem 2025 | P26: 2025
A27: Pinar del Río | B27: 47563.38 | C27: 88920.32 | D27: =SUM(B27:C27) -> 136483.7 | E27: =K7/E7 -> 0.55935369 | F27: =L7/F7 -> 0.15336299 | G27: =M7/G7 -> 0.28070314 | H27: =K7*1000/N7/6 -> 3762.7641 | I27: =L7*1000/O7/6 -> 2257.541 | J27: =M7*1000/P7/12 -> 3010.1526 | K27: =E7*1000/N7/6 -> 6726.9854 | L27: =F7*1000/O7/6 -> 14720.246 | M27: =G7*1000/P7/12 -> 10723.616 | N27: =H27/K27 -> 0.55935369 | O27: =I27/L27 -> 0.15336299 | P27: =J27/M27 -> 0.28070314
A28: Artemisa | B28: 160047.19 | C28: 104660.52 | D28: =SUM(B28:C28) -> 264707.71 | E28: =K8/E8 -> 0.1946907 | F28: =L8/F8 -> 0.2561241 | G28: =M8/G8 -> 0.21993729 | H28: =K8*1000/N8/6 -> 2887.3289 | I28: =L8*1000/O8/6 -> 2650.0489 | J28: =M8*1000/P8/12 -> 2768.6889 | K28: =E8*1000/N8/6 -> 14830.338 | L28: =F8*1000/O8/6 -> 10346.738 | M28: =G8*1000/P8/12 -> 12588.538 | N28: =H28/K28 -> 0.1946907 | O28: =I28/L28 -> 0.2561241 | P28: =J28/M28 -> 0.21993729
A29: Casa Matriz | D29: =SUM(B29:C29) -> 0 | E29: =K9/E9 -> 1.5572995 | F29: =L9/F9 -> 0.73970937 | G29: =M9/G9 -> 0.98904532 | H29: =K9*1000/N9/6 -> 3472.7778 | I29: =L9*1000/O9/6 -> 5155.8095 | J29: =M9*1000/P9/12 -> 4182.49 | K29: =E9*1000/N9/6 -> 2230 | L29: =F9*1000/O9/6 -> 6970.0476 | M29: =G9*1000/P9/12 -> 4228.8153 | N29: =H29/K29 -> 1.5572995 | O29: =I29/L29 -> 0.73970937 | P29: =J29/M29 -> 0.98904532
A30: HABANA | B30: 196253.75 | C30: 111046.73 | D30: =SUM(B30:C30) -> 307300.48 | E30: =K10/E10 -> 0.23295422 | F30: =L10/F10 -> 0.20995623 | G30: =M10/G10 -> 0.22109221 | H30: =K10*1000/N10/6 -> 6056.8732 | I30: =L10*1000/O10/6 -> 5814.823 | J30: =M10*1000/P10/12 -> 5935.8481 | K30: =E10*1000/N10/6 -> 26000.273 | L30: =F10*1000/O10/6 -> 27695.406 | M30: =G10*1000/P10/12 -> 26847.839 | N30: =H30/K30 -> 0.23295422 | O30: =I30/L30 -> 0.20995623 | P30: =J30/M30 -> 0.22109221
A31: MAYABEQUE | B31: 43606.73 | C31: 60792.51 | D31: =SUM(B31:C31) -> 104399.24 | E31: =K11/E11 -> 0.30265037 | F31: =L11/F11 -> 0.24742802 | G31: =M11/G11 -> 0.2751086 | H31: =K11*1000/N11/6 -> 1588.1442 | I31: =L11*1000/O11/6 -> 1840.4521 | J31: =M11*1000/P11/12 -> 1692.2034 | K31: =E11*1000/N11/6 -> 5247.4551 | L31: =F11*1000/O11/6 -> 7438.3333 | M31: =G11*1000/P11/12 -> 6151.0377 | N31: =H31/K31 -> 0.30265037 | O31: =I31/L31 -> 0.24742802 | P31: =J31/M31 -> 0.2751086
A32: Matanzas | B32: 59907.94 | C32: 76274.04 | D32: =SUM(B32:C32) -> 136181.98 | E32: =K12/E12 -> 0.21074236 | F32: =L12/F12 -> 0.15498094 | G32: =M12/G12 -> 0.1773805 | H32: =K12*1000/N12/6 -> 3691.7654 | I32: =L12*1000/O12/6 -> 4043.6294 | J32: =M12*1000/P12/12 -> 3867.6974 | K32: =E12*1000/N12/6 -> 17517.909 | L32: =F12*1000/O12/6 -> 26091.14 | M32: =G12*1000/P12/12 -> 21804.524 | N32: =H32/K32 -> 0.21074236 | O32: =I32/L32 -> 0.15498094 | P32: =J32/M32 -> 0.1773805
A33: Villa Clara | B33: 23537.47 | C33: 25365.78 | D33: =SUM(B33:C33) -> 48903.25 | E33: =K13/E13 -> 0.49119896 | F33: =L13/F13 -> 0.51642434 | G33: =M13/G13 -> 0.50371053 | H33: =K13*1000/N13/6 -> 2505.7318 | I33: =L13*1000/O13/6 -> 2592.5053 | J33: =M13*1000/P13/12 -> 2549.1186 | K33: =E13*1000/N13/6 -> 5101.2564 | L33: =F13*1000/O13/6 -> 5020.1068 | M33: =G13*1000/P13/12 -> 5060.6816 | N33: =H33/K33 -> 0.49119896 | O33: =I33/L33 -> 0.51642434 | P33: =J33/M33 -> 0.50371053
A34: Cienfuegos | B34: 50325.11 | C34: 62112.22 | D34: =SUM(B34:C34) -> 112437.33 | E34: =K14/E14 -> 0.30642421 | F34: =L14/F14 -> 0.30475771 | G34: =M14/G14 -> 0.30553388 | H34: =K14*1000/N14/6 -> 3373.2297 | I34: =L14*1000/O14/6 -> 3848.3413 | J34: =M14*1000/P14/12 -> 3610.7855 | K34: =E14*1000/N14/6 -> 11008.365 | L34: =F14*1000/O14/6 -> 12627.544 | M34: =G14*1000/P14/12 -> 11817.955 | N34: =H34/K34 -> 0.30642421 | O34: =I34/L34 -> 0.30475771 | P34: =J34/M34 -> 0.30553388
A35: Sancti Spíritus | B35: 48557.02 | C35: 46417.36 | D35: =SUM(B35:C35) -> 94974.38 | E35: =K15/E15 -> 0.44485796 | F35: =L15/F15 -> 0.2963919 | G35: =M15/G15 -> 0.3595843 | H35: =K15*1000/N15/6 -> 4254.2014 | I35: =L15*1000/O15/6 -> 2458.8244 | J35: =M15*1000/P15/12 -> 3161.3632 | K35: =E15*1000/N15/6 -> 9563.0556 | L35: =F15*1000/O15/6 -> 8295.8557 | M35: =G15*1000/P15/12 -> 8791.7165 | N35: =H35/K35 -> 0.44485796 | O35: =I35/L35 -> 0.2963919 | P35: =J35/M35 -> 0.3595843
A36: Ciego de Avila | B36: 23045.83 | C36: 20330.95 | D36: =SUM(B36:C36) -> 43376.78 | E36: =K16/E16 -> 0.31723211 | F36: =L16/F16 -> 0.41906327 | G36: =M16/G16 -> 0.36548723 | H36: =K16*1000/N16/6 -> 1168.4952 | I36: =L16*1000/O16/6 -> 2635.3068 | J36: =M16*1000/P16/12 -> 1675.0745 | K36: =E16*1000/N16/6 -> 3683.4077 | L36: =F16*1000/O16/6 -> 6288.5655 | M36: =G16*1000/P16/12 -> 4583.1271 | N36: =H36/K36 -> 0.31723211 | O36: =I36/L36 -> 0.41906327 | P36: =J36/M36 -> 0.36548723
A37: Camagüey | B37: 96334.79 | C37: 113762.35 | D37: =SUM(B37:C37) -> 210097.14 | E37: =K17/E17 -> 0.1934818 | F37: =L17/F17 -> 0.14364933 | G37: =M17/G17 -> 0.16664412 | H37: =K17*1000/N17/6 -> 3174.7158 | I37: =L17*1000/O17/6 -> 1982.5326 | J37: =M17*1000/P17/12 -> 2481.8561 | K37: =E17*1000/N17/6 -> 16408.343 | L37: =F17*1000/O17/6 -> 13801.196 | M37: =G17*1000/P17/12 -> 14893.151 | N37: =H37/K37 -> 0.1934818 | O37: =I37/L37 -> 0.14364933 | P37: =J37/M37 -> 0.16664412
A38: Las Tunas | B38: 22608.94 | C38: 22564.32 | D38: =SUM(B38:C38) -> 45173.26 | E38: =K18/E18 -> 0.41562695 | F38: =L18/F18 -> 0.40691409 | G38: =M18/G18 -> 0.41158938 | H38: =K18*1000/N18/6 -> 2675.7489 | I38: =L18*1000/O18/6 -> 2262.3348 | J38: =M18*1000/P18/12 -> 2469.0419 | K38: =E18*1000/N18/6 -> 6437.8619 | L38: =F18*1000/O18/6 -> 5559.7357 | M38: =G18*1000/P18/12 -> 5998.7988 | N38: =H38/K38 -> 0.41562695 | O38: =I38/L38 -> 0.40691409 | P38: =J38/M38 -> 0.41158938
A39: Holguín | B39: 81865.29 | C39: 123106.71 | D39: =SUM(B39:C39) -> 204972 | E39: =K19/E19 -> 0.35580467 | F39: =L19/F19 -> 0.30257119 | G39: =M19/G19 -> 0.32305618 | H39: =K19*1000/N19/6 -> 3032.8521 | I39: =L19*1000/O19/6 -> 4123.0892 | J39: =M19*1000/P19/12 -> 3577.9706 | K39: =E19*1000/N19/6 -> 8523.9243 | L39: =F19*1000/O19/6 -> 13626.84 | M39: =G19*1000/P19/12 -> 11075.382 | N39: =H39/K39 -> 0.35580467 | O39: =I39/L39 -> 0.30257119 | P39: =J39/M39 -> 0.32305618
A40: Granma | B40: 44907.18 | C40: 41945.09 | D40: =SUM(B40:C40) -> 86852.27 | E40: =K20/E20 -> 0.15648564 | F40: =L20/F20 -> 0.23211396 | G40: =M20/G20 -> 0.19263346 | H40: =K20*1000/N20/6 -> 2343.2211 | I40: =L20*1000/O20/6 -> 3182.2884 | J40: =M20*1000/P20/12 -> 2762.7547 | K40: =E20*1000/N20/6 -> 14974.033 | L40: =F20*1000/O20/6 -> 13710.026 | M40: =G20*1000/P20/12 -> 14342.029 | N40: =H40/K40 -> 0.15648564 | O40: =I40/L40 -> 0.23211396 | P40: =J40/M40 -> 0.19263346
A41: Stgo Cuba | B41: 56287.15 | C41: 34888.18 | D41: =SUM(B41:C41) -> 91175.33 | E41: =K21/E21 -> 0.2183707 | F41: =L21/F21 -> 0.34425739 | G41: =M21/G21 -> 0.26367388 | H41: =K21*1000/N21/6 -> 3273.6894 | I41: =L21*1000/O21/6 -> 2901.4091 | J41: =M21*1000/P21/12 -> 3087.5492 | K41: =E21*1000/N21/6 -> 14991.432 | L41: =F21*1000/O21/6 -> 8428.0227 | M41: =G21*1000/P21/12 -> 11709.727 | N41: =H41/K41 -> 0.2183707 | O41: =I41/L41 -> 0.34425739 | P41: =J41/M41 -> 0.26367388
A42: Guantanamo | B42: 25153.57 | C42: 20446.81 | D42: =SUM(B42:C42) -> 45600.38 | E42: =K22/E22 -> 0.49679374 | F42: =L22/F22 -> 0.51947908 | G42: =M22/G22 -> 0.50700928 | H42: =K22*1000/N22/6 -> 3460.0267 | I42: =L22*1000/O22/6 -> 2963.9661 | J42: =M22*1000/P22/12 -> 3211.9964 | K42: =E22*1000/N22/6 -> 6964.7148 | L42: =F22*1000/O22/6 -> 5705.6506 | M42: =G22*1000/P22/12 -> 6335.1827 | N42: =H42/K42 -> 0.49679374 | O42: =I42/L42 -> 0.51947908 | P42: =J42/M42 -> 0.50700928
A43: TOTAL | B43: =SUM(B27:B42) -> 980001.34 | C43: =SUM(C27:C42) -> 952633.89 | D43: =SUM(B43:C43) -> 1932635.2 | E43: =K23/E23 -> 0.29122356 | F43: =L23/F23 -> 0.25572877 | H43: =K23*1000/N23/6 -> 2938.0901 | I43: =L23*1000/O23/6 -> 2976.6299 | J43: =M23*1000/P23/12 -> 2956.975 | K43: =E23*1000/N23/6 -> 10088.779 | L43: =F23*1000/O23/6 -> 11639.793 | M43: =G23*1000/P23/12 -> 10848.794 | N43: =H43/K43 -> 0.29122356 | O43: =I43/L43 -> 0.25572877 | P43: =J43/M43 -> 0.27256256

Sheet P 14-B
D1: 366 | E1: 375 | F1: 226 | G1: 35 | H1: =520-71 -> 449 | I1: 152 | J1: 312 | K1: 209 | L1: 224 | M1: 201 | N1: 358 | O1: 227 | P1: 471 | Q1: 193 | R1: 220 | S1: 187 | T1: =SUM(D1:S1) -> 4205
B2: Promedio Trabajadores | D2: =D35-D1 -> 6 | E2: =E35-E1 -> -66 | F2: =F35-F1 -> 9 | G2: =G35-G1 -> 21 | H2: =H35-H1 -> -85 | I2: =I35-I1 -> 21 | J2: =J35-J1 -> 9 | K2: =K35-K1 -> 2 | ... T2: =T35-T1 -> 3
B3: Grupo Complejidad | C3: Salario Escala | D3: PRI | E3: ART | F3: HAB | G3: CMATRIZ | H3: MAY | I3: MAT | J3: VCL | K3: CFG | L3: SSP | M3: CAV | N3: CMG | O3: LTU | P3: HLG | Q3: GRM | R3: SCU | S3: GTM | T3: Consolidado
B5: I | C5: 3210 | D5: 3 | E5: 4 | F5: 3 | G5: 3 | H5: 2 | I5: 2 | J5: 4 | K5: 4 | L5: 4 | M5: 4 | N5: 4 | O5: 3 | P5: 4 | Q5: 4 | R5: 4 | S5: 4 | T5: =SUM(D5:S5) -> 56
B6: II | C6: 3362.8571 | D6: 12 | E6: 14 | F6: 19 | G6: 4 | H6: 38 | I6: 7 | J6: 39 | K6: 18 | L6: 3 | M6: 28 | N6: 12 | O6: 23 | P6: 28 | Q6: 12 | R6: 28 | S6: 25 | T6: =SUM(D6:S6) -> 310
B7: III | C7: 3515.7143 | D7: 15 | E7: 23 | F7: 18 | G7: 3 | H7: 37 | I7: 12 | J7: 40 | K7: 22 | L7: 15 | M7: 17 | N7: 44 | O7: 13 | P7: 32 | Q7: 15 | R7: 19 | S7: 21 | T7: =SUM(D7:S7) -> 346
B8: IV | C8: 3699.1429 | D8: 24 | E8: 30 | F8: 19 | G8: 4 | H8: 44 | I8: 18 | J8: 28 | K8: 18 | L8: 1 | M8: 31 | N8: 47 | O8: 5 | P8: 45 | Q8: 1 | R8: 18 | S8: 22 | T8: =SUM(D8:S8) -> 355
B9: V | C9: 3882.5714 | D9: 81 | E9: 38 | F9: 16 | G9: 1 | H9: 37 | I9: 18 | J9: 80 | K9: 40 | L9: 52 | M9: 35 | N9: 81 | O9: 43 | P9: 63 | Q9: 40 | R9: 48 | S9: 40 | T9: =SUM(D9:S9) -> 713
B10: VI | C10: 4066 | D10: 90 | E10: 74 | F10: 35 | H10: 37 | I10: 25 | J10: 41 | K10: 23 | L10: 58 | M10: 37 | N10: 75 | O10: 45 | P10: 17 | Q10: 46 | R10: 57 | S10: 45 | T10: =SUM(D10:S10) -> 705
B11: VII | C11: 4295.2857 | D11: 20 | E11: 15 | F11: 4 | G11: 4 | H11: 27 | I11: 17 | K11: 14 | L11: 25 | M11: 11 | N11: 6 | O11: 17 | Q11: 17 | R11: 1 | S11: 15 | T11: =SUM(D11:S11) -> 193
B12: VIII | C12: 4524.5714 | D12: 22 | E12: 15 | F12: 22 | G12: 3 | H12: 24 | I12: 15 | J12: 28 | K12: 18 | L12: 1 | M12: 10 | N12: 26 | O12: 15 | P12: 50 | Q12: 4 | R12: 10 | S12: 17 | T12: =SUM(D12:S12) -> 280
B13: IX | C13: 4753.8571 | D13: 30 | E13: 17 | F13: 15 | H13: 36 | I13: 10 | J13: 11 | K13: 4 | L13: 1 | M13: 7 | N13: 10 | O13: 11 | P13: 51 | Q13: 4 | R13: 7 | S13: 1 | T13: =SUM(D13:S13) -> 215
B14: X | C14: 4983.1429 | D14: 24 | E14: 25 | F14: 13 | H14: 16 | I14: 21 | J14: 20 | K14: 12 | L14: 3 | M14: 4 | N14: 10 | O14: 12 | P14: 50 | Q14: 3 | R14: 4 | S14: 6 | T14: =SUM(D14:S14) -> 223
B15: XI | C15: 5212.4286 | D15: 17 | E15: 21 | F15: 24 | H15: 36 | I15: 13 | J15: 16 | K15: 15 | L15: 31 | M15: 8 | N15: 40 | O15: 24 | P15: 52 | Q15: 27 | R15: 22 | S15: 18 | T15: =SUM(D15:S15) -> 364
B16: XII | C16: 5518.1429 | D16: 14 | E16: 15 | F16: 35 | J16: 4 | K16: 10 | L16: 12 | M16: 1 | N16: 4 | O16: 6 | P16: 40 | Q16: 12 | R16: 1 | S16: 1 | T16: =SUM(D16:S16) -> 155
B17: XIII | C17: 5823.8571 | D17: 10 | E17: 10 | F17: 6 | G17: 16 | H17: 22 | I17: 8 | K17: 7 | L17: 12 | M17: 3 | N17: 1 | O17: 1 | P17: 39 | Q17: 12 | R17: 3 | S17: 5 | T17: =SUM(D17:S17) -> 155
B18: XIV | C18: 6129.5714 | D18: 8 | E18: 6 | F18: 4 | H18: 6 | I18: 5 | J18: 8 | K18: 4 | L18: 6 | M18: 5 | N18: 6 | O18: 8 | P18: 10 | Q18: 4 | R18: 6 | S18: 4 | T18: =SUM(D18:S18) -> 90
B19: XV | C19: 6435.2857 | G19: 1 | T19: =SUM(D19:S19) -> 1
B20: XVI | C20: 6741 | T20: =SUM(D20:S20) -> 0
B21: XVII | C21: 7046.7143 | T21: =SUM(D21:S21) -> 0
B22: XVIII | C22: 7352.4286 | T22: =SUM(D22:S22) -> 0
B23: XIX | C23: 7734.5714 | T23: =SUM(D23:S23) -> 0
B24: XX | C24: 8116.7143 | D24: 1 | E24: 1 | F24: 1 | H24: 1 | I24: 1 | J24: 1 | K24: 1 | L24: 1 | M24: 1 | N24: 1 | O24: 1 | P24: 1 | Q24: 1 | R24: 1 | S24: 1 | T24: =SUM(D24:S24) -> 15
B25: XXI | C25: 8498.8571 | D25: 1 | E25: 1 | F25: 1 | G25: 3 | H25: 1 | I25: 1 | J25: 1 | K25: 1 | L25: 1 | M25: 1 | N25: 1 | O25: 1 | P25: 1 | Q25: 1 | R25: 1 | S25: 1 | T25: =SUM(D25:S25) -> 18
B26: XXII | C26: 8881 | G26: 10 | T26: =SUM(D26:S26) -> 10
B27: XXIII | C27: 9263.1429 | G27: 2 | T27: =SUM(D27:S27) -> 2
B28: XXIV | C28: 9645.2857 | G28: 1 | T28: =SUM(D28:S28) -> 1
B29: XXV | C29: 10103.857 | G29: 1 | T29: =SUM(D29:S29) -> 1
T30: =SUM(D30:S30) -> 0
T31: =SUM(D31:S31) -> 0
T32: =SUM(D32:S32) -> 0
T33: =SUM(D33:S33) -> 0
D34: =$C$5*D5+$C$6*D6+$C$7*D7+$C$8*D8+$C$9*D9+$C$10*D10+$C$11*D11+$C$12*D12+$C$13*D13+$C$14*D14+$C$15*D15+$C$16*D16+$C$17*D17+$C$18*D18+$C$19*D19+$C$20*D20+$C$21*D21+$C$22*D22+$C$23*D23+$C$24*D24+$C$25*D25+$C$26*D26+$C$27*D27+$C$28*D28+$C$29*D29+$C$30*D30+$C$31*D31+$C$32*D32+$C$33*D33 -> 1609341.1 | E34: =$C$5*E5+$C$6*E6+$C$7*E7+$C$8*E8+$C$9*E9+$C$10*E10+$C$11*E11+$C$12*E12+$C$13*E13+$C$14*E14+$C$15*E15+$C$16*E16+$C$17*E17+$C$18*E18+$C$19*E19+$C$20*E20+$C$21*E21+$C$22*E22+$C$23*E23+$C$24*E24+$C$25*E25+$C$26*E26+$C$27*E27+$C$28*E28+$C$29*E29+$C$30*E30+$C$31*E31+$C$32*E32+$C$33*E33 -> 1341734.1 | F34: =$C$5*F5+$C$6*F6+$C$7*F7+$C$8*F8+$C$9*F9+$C$10*F10+$C$11*F11+$C$12*F12+$C$13*F13+$C$14*F14+$C$15*F15+$C$16*F16+$C$17*F17+$C$18*F18+$C$19*F19+$C$20*F20+$C$21*F21+$C$22*F22+$C$23*F23+$C$24*F24+$C$25*F25+$C$26*F26+$C$27*F27+$C$28*F28+$C$29*F29+$C$30*F30+$C$31*F31+$C$32*F32+$C$33*F33 -> 1058642.7 | G34: =$C$5*G5+$C$6*G6+$C$7*G7+$C$8*G8+$C$9*G9+$C$10*G10+$C$11*G11+$C$12*G12+$C$13*G13+$C$14*G14+$C$15*G15+$C$16*G16+$C$17*G17+$C$18*G18+$C$19*G19+$C$20*G20+$C$21*G21+$C$22*G22+$C$23*G23+$C$24*G24+$C$25*G25+$C$26*G26+$C$27*G27+$C$28*G28+$C$29*G29+$C$30*G30+$C$31*G31+$C$32*G32+$C$33*G33 -> 335261.57 | H34: =$C$5*H5+$C$6*H6+$C$7*H7+$C$8*H8+$C$9*H9+$C$10*H10+$C$11*H11+$C$12*H12+$C$13*H13+$C$14*H14+$C$15*H15+$C$16*H16+$C$17*H17+$C$18*H18+$C$19*H19+$C$20*H20+$C$21*H21+$C$22*H22+$C$23*H23+$C$24*H24+$C$25*H25+$C$26*H26+$C$27*H27+$C$28*H28+$C$29*H29+$C$30*H30+$C$31*H31+$C$32*H32+$C$33*H33 -> 1565746.3 | I34: =$C$5*I5+$C$6*I6+$C$7*I7+$C$8*I8+$C$9*I9+$C$10*I10+$C$11*I11+$C$12*I12+$C$13*I13+$C$14*I14+$C$15*I15+$C$16*I16+$C$17*I17+$C$18*I18+$C$19*I19+$C$20*I20+$C$21*I21+$C$22*I22+$C$23*I23+$C$24*I24+$C$25*I25+$C$26*I26+$C$27*I27+$C$28*I28+$C$29*I29+$C$30*I30+$C$31*I31+$C$32*I32+$C$33*I33 -> 764958.29 | J34: =$C$5*J5+$C$6*J6+$C$7*J7+$C$8*J8+$C$9*J9+$C$10*J10+$C$11*J11+$C$12*J12+$C$13*J13+$C$14*J14+$C$15*J15+$C$16*J16+$C$17*J17+$C$18*J18+$C$19*J19+$C$20*J20+$C$21*J21+$C$22*J22+$C$23*J23+$C$24*J24+$C$25*J25+$C$26*J26+$C$27*J27+$C$28*J28+$C$29*J29+$C$30*J30+$C$31*J31+$C$32*J32+$C$33*J33 -> 1315274.6 | K34: =$C$5*K5+$C$6*K6+$C$7*K7+$C$8*K8+$C$9*K9+$C$10*K10+$C$11*K11+$C$12*K12+$C$13*K13+$C$14*K14+$C$15*K15+$C$16*K16+$C$17*K17+$C$18*K18+$C$19*K19+$C$20*K20+$C$21*K21+$C$22*K22+$C$23*K23+$C$24*K24+$C$25*K25+$C$26*K26+$C$27*K27+$C$28*K28+$C$29*K29+$C$30*K30+$C$31*K31+$C$32*K32+$C$33*K33 -> 901780.71 | ... T34: =$C$5*T5+$C$6*T6+$C$7*T7+$C$8*T8+$C$9*T9+$C$10*T10+$C$11*T11+$C$12*T12+$C$13*T13+$C$14*T14+$C$15*T15+$C$16*T16+$C$17*T17+$C$18*T18+$C$19*T19+$C$20*T20+$C$21*T21+$C$22*T22+$C$23*T23+$C$24*T24+$C$25*T25+$C$26*T26+$C$27*T27+$C$28*T28+$C$29*T29+$C$30*T30+$C$31*T31+$C$32*T32+$C$33*T33 -> 18231119
B35: Promedio de Trabajadores | D35: =SUM(D5:D33) -> 372 | E35: =SUM(E5:E33) -> 309 | F35: =SUM(F5:F33) -> 235 | G35: =SUM(G5:G33) -> 56 | H35: =SUM(H5:H33) -> 364 | I35: =SUM(I5:I33) -> 173 | J35: =SUM(J5:J33) -> 321 | K35: =SUM(K5:K33) -> 211 | ... T35: =SUM(T5:T33) -> 4208
B36: Salario Agosto-Diciembre | D36: =D34*5/1000 -> 8046.7057 | E36: =E34*5/1000 -> 6708.6707 | F36: =F34*5/1000 -> 5293.2136 | G36: =G34*5/1000 -> 1676.3079 | H36: =H34*5/1000 -> 7828.7314 | I36: =I34*5/1000 -> 3824.7914 | J36: =J34*5/1000 -> 6576.3729 | K36: =K34*5/1000 -> 4508.9036 | ... T36: =T34*5/1000 -> 91155.593 | U36: =SUM(T36:T36,T39) -> 164755.74
B37: Pago 10 USD | D37: =D35*120/1000*5 -> 223.2 | E37: =E35*120/1000*5 -> 185.4 | F37: =F35*120/1000*5 -> 141 | G37: =G35*120/1000*5 -> 33.6 | H37: =H35*120/1000*5 -> 218.4 | I37: =I35*120/1000*5 -> 103.8 | J37: =J35*120/1000*5 -> 192.6 | K37: =K35*120/1000*5 -> 126.6 | ... T37: =T35*120/1000*5 -> 2524.8
B38: Salario Julio | D38: 1341.65 | E38: 955.7 | F38: 1232.13 | G38: 163.72 | H38: 768.07 | I38: 1251 | J38: 877.95 | K38: 840.92 | L38: 535.61 | M38: 407.37 | N38: 734.39 | O38: 504.87 | P38: 1116.29 | Q38: 609.72 | R38: 582.98 | S38: 533.49 | T38: =SUM(D38:S38) -> 12455.86
B39: Salario Enero - Junio | D39: ='EMPLEO Y SALARIO'!L7 -> 4957.56 | E39: ='EMPLEO Y SALARIO'!L8 -> 5962.61 | F39: ='EMPLEO Y SALARIO'!L10 -> 7884.9 | G39: ='EMPLEO Y SALARIO'!L9 -> 1082.72 | H39: ='EMPLEO Y SALARIO'!L11 -> 4030.59 | I39: ='EMPLEO Y SALARIO'!L12 -> 3687.79 | J39: ='EMPLEO Y SALARIO'!L13 -> 4853.17 | K39: ='EMPLEO Y SALARIO'!L14 -> 4825.82 | L39: ='EMPLEO Y SALARIO'!L15 -> 3304.66 | M39: ='EMPLEO Y SALARIO'!L16 -> 3178.18 | N39: ='EMPLEO Y SALARIO'!L17 -> 4258.48 | O39: ='EMPLEO Y SALARIO'!L18 -> 3081.3 | P39: ='EMPLEO Y SALARIO'!L19 -> 11651.85 | Q39: ='EMPLEO Y SALARIO'!L20 -> 3685.09 | R39: ='EMPLEO Y SALARIO'!L21 -> 3829.86 | S39: ='EMPLEO Y SALARIO'!L22 -> 3325.57 | T39: =SUM(D39:S39) -> 73600.15
B40: Fondo Salario | D40: =SUM(D36:D39) -> 14569.116 | E40: =SUM(E36:E39) -> 13812.381 | F40: =SUM(F36:F39) -> 14551.244 | G40: =SUM(G36:G39) -> 2956.3479 | H40: =SUM(H36:H39) -> 12845.791 | I40: =SUM(I36:I39) -> 8867.3814 | J40: =SUM(J36:J39) -> 12500.093 | K40: =SUM(K36:K39) -> 10302.244 | ... S40: =SUM(S36:S39) -> 8674.6107 | T40: =SUM(D40:S40) -> 179736.4
B41: Gasto salario/Ingreso Total | D41: =D40/'EMPLEO Y SALARIO'!D7 -> 0.1060585 | E41: =E40/'EMPLEO Y SALARIO'!D8 -> 0.052123379 | F41: =F40/'EMPLEO Y SALARIO'!D10 -> 0.050681135 | G41: =G40/'EMPLEO Y SALARIO'!D9 -> 0.078741621 | H41: =H40/'EMPLEO Y SALARIO'!D11 -> 0.1154055 | I41: =I40/'EMPLEO Y SALARIO'!D12 -> 0.064929161 | J41: =J40/'EMPLEO Y SALARIO'!D13 -> 0.2470731 | K41: =K40/'EMPLEO Y SALARIO'!D14 -> 0.091042475 | L41: =L40/'EMPLEO Y SALARIO'!D15 -> 0.094320751 | M41: =M40/'EMPLEO Y SALARIO'!D16 -> 0.17989994 | N41: =N40/'EMPLEO Y SALARIO'!D17 -> 0.061108709 | O41: =O40/'EMPLEO Y SALARIO'!D18 -> 0.18847698 | P41: =P40/'EMPLEO Y SALARIO'!D19 -> 0.11723611 | Q41: =Q40/'EMPLEO Y SALARIO'!D20 -> 0.10204811 | R41: =R40/'EMPLEO Y SALARIO'!D21 -> 0.10050319 | S41: =S40/'EMPLEO Y SALARIO'!D22 -> 0.1833343 | T41: =T40/'EMPLEO Y SALARIO'!D23 -> 0.091386179
B44: Fondo Salario 2026 | D44: =D34*12/1000 -> 19312.094 | E44: =E34*12/1000 -> 16100.81 | F44: =F34*12/1000 -> 12703.713 | G44: =G34*12/1000 -> 4023.1389 | H44: =H34*12/1000 -> 18788.955 | I44: =I34*12/1000 -> 9179.4994 | J44: =J34*12/1000 -> 15783.295 | K44: =K34*12/1000 -> 10821.369 | ... T44: =T34*12/1000 -> 218773.42
D45: =1200*12*D35/1000 -> 5356.8 | E45: =1200*12*E35/1000 -> 4449.6 | F45: =1200*12*F35/1000 -> 3384 | G45: =1200*12*G35/1000 -> 806.4 | H45: =1200*12*H35/1000 -> 5241.6 | I45: =1200*12*I35/1000 -> 2491.2 | J45: =1200*12*J35/1000 -> 4622.4 | K45: =1200*12*K35/1000 -> 3038.4 | ... T45: =1200*12*T35/1000 -> 60595.2
D46: =SUM(D44:D44) -> 19312.094 | E46: =SUM(E44:E44) -> 16100.81 | F46: =SUM(F44:F44) -> 12703.713 | G46: =SUM(G44:G44) -> 4023.1389 | H46: =SUM(H44:H44) -> 18788.955 | I46: =SUM(I44:I44) -> 9179.4994 | J46: =SUM(J44:J44) -> 15783.295 | K46: =SUM(K44:K44) -> 10821.369 | ... T46: =SUM(T44:T44) -> 218773.42
C48: =C39+C36+C38 -> 0 | D48: =D39+D36+D38 -> 14345.916 | E48: =E39+E36+E38 -> 13626.981 | F48: =F39+F36+F38 -> 14410.244 | G48: =G39+G36+G38 -> 2922.7479 | H48: =H39+H36+H38 -> 12627.391 | I48: =I39+I36+I38 -> 8763.5814 | J48: =J39+J36+J38 -> 12307.493 | ... T48: =T39+T36+T38 -> 177211.6 | U48: =T48+T49 -> 230375.08
D49: =D48*0.3 -> 4303.7747 | E49: =E48*0.3 -> 4088.0942 | F49: =F48*0.3 -> 4323.0731 | G49: =G48*0.3 -> 876.82436 | H49: =H48*0.3 -> 3788.2174 | I49: =I48*0.3 -> 2629.0744 | J49: =J48*0.3 -> 3692.2479 | K49: =K48*0.3 -> 3052.6931 | ... T49: =T48*0.3 -> 53163.481
D50: =D35*1200*12/1000 -> 5356.8 | E50: =E35*1200*12/1000 -> 4449.6 | F50: =F35*1200*12/1000 -> 3384 | G50: =G35*1200*12/1000 -> 806.4 | H50: =H35*1200*12/1000 -> 5241.6 | I50: =I35*1200*12/1000 -> 2491.2 | J50: =J35*1200*12/1000 -> 4622.4 | K50: =K35*1200*12/1000 -> 3038.4 | ... T50: =T35*1200*12/1000 -> 60595.2
D53: =SUM(D48:D49) -> 18649.69 | E53: =SUM(E48:E49) -> 17715.075 | F53: =SUM(F48:F49) -> 18733.317 | G53: =SUM(G48:G49) -> 3799.5722 | H53: =SUM(H48:H49) -> 16415.609 | I53: =SUM(I48:I49) -> 11392.656 | J53: =SUM(J48:J49) -> 15999.741 | K53: =SUM(K48:K49) -> 13228.337 | ... T53: =SUM(T48:T49) -> 230375.08

Sheet P 14-B (2)
D1: 366 | E1: 375 | F1: 226 | G1: 35 | H1: =520-71 -> 449 | I1: 152 | J1: 312 | K1: 209 | L1: 224 | M1: 201 | N1: 358 | O1: 227 | P1: 471 | Q1: 193 | R1: 220 | S1: 187 | T1: =SUM(D1:S1) -> 4205
B2: Promedio Trabajadores | D2: =D35-D1 -> 6 | E2: =E35-E1 -> -66 | F2: =F35-F1 -> 9 | G2: =G35-G1 -> 21 | H2: =H35-H1 -> -85 | I2: =I35-I1 -> 21 | J2: =J35-J1 -> 9 | K2: =K35-K1 -> 2 | ... T2: =T35-T1 -> 3
B3: Grupo Complejidad | C3: Salario Escala | D3: PRI | E3: ART | F3: HAB | G3: CMATRIZ | H3: MAY | I3: MAT | J3: VCL | K3: CFG | L3: SSP | M3: CAV | N3: CMG | O3: LTU | P3: HLG | Q3: GRM | R3: SCU | S3: GTM | T3: Consolidado
B5: I | C5: 6300 | D5: 3 | E5: 4 | F5: 3 | G5: 3 | H5: 2 | I5: 2 | J5: 4 | K5: 4 | L5: 4 | M5: 4 | N5: 4 | O5: 3 | P5: 4 | Q5: 4 | R5: 4 | S5: 4 | T5: =SUM(D5:S5) -> 56 | W5: CMViejo
B6: II | C6: 6600 | D6: 12 | E6: 14 | F6: 19 | G6: 4 | H6: 38 | I6: 7 | J6: 39 | K6: 18 | L6: 3 | M6: 28 | N6: 12 | O6: 23 | P6: 28 | Q6: 12 | R6: 28 | S6: 25 | T6: =SUM(D6:S6) -> 310 | W6: 2
B7: III | C7: 6900 | D7: 15 | E7: 23 | F7: 18 | G7: 3 | H7: 37 | I7: 12 | J7: 40 | K7: 22 | L7: 15 | M7: 17 | N7: 44 | O7: 13 | P7: 32 | Q7: 15 | R7: 19 | S7: 21 | T7: =SUM(D7:S7) -> 346 | W7: 1
B8: IV | C8: 7260 | D8: 24 | E8: 30 | F8: 19 | G8: 4 | H8: 44 | I8: 18 | J8: 28 | K8: 18 | L8: 1 | M8: 31 | N8: 47 | O8: 5 | P8: 45 | Q8: 1 | R8: 18 | S8: 22 | T8: =SUM(D8:S8) -> 355 | W8: 4
B9: V | C9: 7620 | D9: 81 | E9: 38 | F9: 16 | G9: 1 | H9: 37 | I9: 18 | J9: 80 | K9: 40 | L9: 52 | M9: 35 | N9: 81 | O9: 43 | P9: 63 | Q9: 40 | R9: 48 | S9: 40 | T9: =SUM(D9:S9) -> 713 | W9: 3
B10: VI | C10: 7980 | D10: 90 | E10: 74 | F10: 35 | H10: 37 | I10: 25 | J10: 41 | K10: 23 | L10: 58 | M10: 37 | N10: 75 | O10: 45 | P10: 17 | Q10: 46 | R10: 57 | S10: 45 | T10: =SUM(D10:S10) -> 705 | W10: 3
B11: VII | C11: 8430 | D11: 20 | E11: 15 | F11: 4 | G11: 4 | H11: 27 | I11: 17 | K11: 14 | L11: 25 | M11: 11 | N11: 6 | O11: 17 | Q11: 17 | R11: 1 | S11: 15 | T11: =SUM(D11:S11) -> 193
B12: VIII | C12: 8880 | D12: 22 | E12: 15 | F12: 22 | G12: 3 | H12: 24 | I12: 15 | J12: 28 | K12: 18 | L12: 1 | M12: 10 | N12: 26 | O12: 15 | P12: 50 | Q12: 4 | R12: 10 | S12: 17 | T12: =SUM(D12:S12) -> 280
B13: IX | C13: 9330 | D13: 30 | E13: 17 | F13: 15 | H13: 36 | I13: 10 | J13: 11 | K13: 4 | L13: 1 | M13: 7 | N13: 10 | O13: 11 | P13: 51 | Q13: 4 | R13: 7 | S13: 1 | T13: =SUM(D13:S13) -> 215
B14: X | C14: 9780 | D14: 24 | E14: 25 | F14: 13 | H14: 16 | I14: 21 | J14: 20 | K14: 12 | L14: 3 | M14: 4 | N14: 10 | O14: 12 | P14: 50 | Q14: 3 | R14: 4 | S14: 6 | T14: =SUM(D14:S14) -> 223 | W14: 2
B15: XI | C15: 10230 | D15: 17 | E15: 21 | F15: 24 | H15: 36 | I15: 13 | J15: 16 | K15: 15 | L15: 31 | M15: 8 | N15: 40 | O15: 24 | P15: 52 | Q15: 27 | R15: 22 | S15: 18 | T15: =SUM(D15:S15) -> 364 | W15: 2
B16: XII | C16: 10830 | D16: 14 | E16: 15 | F16: 35 | J16: 4 | K16: 10 | L16: 12 | M16: 1 | N16: 4 | O16: 6 | P16: 40 | Q16: 12 | R16: 1 | S16: 1 | T16: =SUM(D16:S16) -> 155 | W16: 3
B17: XIII | C17: 11430 | D17: 10 | E17: 10 | F17: 6 | G17: 16 | H17: 22 | I17: 8 | K17: 7 | L17: 12 | M17: 3 | N17: 1 | O17: 1 | P17: 39 | Q17: 12 | R17: 3 | S17: 5 | T17: =SUM(D17:S17) -> 155
B18: XIV | C18: 12030 | D18: 8 | E18: 6 | F18: 4 | H18: 6 | I18: 5 | J18: 8 | K18: 4 | L18: 6 | M18: 5 | N18: 6 | O18: 8 | P18: 10 | Q18: 4 | R18: 6 | S18: 4 | T18: =SUM(D18:S18) -> 90
B19: XV | C19: 12630 | G19: 1 | T19: =SUM(D19:S19) -> 1
B20: XVI | C20: 13230 | T20: =SUM(D20:S20) -> 0
B21: XVII | C21: 13830 | T21: =SUM(D21:S21) -> 0 | W21: 6
B22: XVIII | C22: 14430 | T22: =SUM(D22:S22) -> 0 | W22: 2
B23: XIX | C23: 15180 | T23: =SUM(D23:S23) -> 0
B24: XX | C24: 15930 | D24: 1 | E24: 1 | F24: 1 | H24: 1 | I24: 1 | J24: 1 | K24: 1 | L24: 1 | M24: 1 | N24: 1 | O24: 1 | P24: 1 | Q24: 1 | R24: 1 | S24: 1 | T24: =SUM(D24:S24) -> 15 | W24: 3
B25: XXI | C25: 16680 | D25: 1 | E25: 1 | F25: 1 | G25: 3 | H25: 1 | I25: 1 | J25: 1 | K25: 1 | L25: 1 | M25: 1 | N25: 1 | O25: 1 | P25: 1 | Q25: 1 | R25: 1 | S25: 1 | T25: =SUM(D25:S25) -> 18
B26: XXII | C26: 17430 | G26: 10 | T26: =SUM(D26:S26) -> 10
B27: XXIII | C27: 18180 | G27: 2 | T27: =SUM(D27:S27) -> 2
B28: XXIV | C28: 18930 | G28: 1 | T28: =SUM(D28:S28) -> 1 | W28: 3
B29: XXV | C29: 21150 | G29: 1 | T29: =SUM(D29:S29) -> 1 | W29: 4
T30: =SUM(D30:S30) -> 0 | W30: 10
T31: =SUM(D31:S31) -> 0 | W31: 2
T32: =SUM(D32:S32) -> 0 | W32: 1
T33: =SUM(D33:S33) -> 0 | W33: 1
D34: =$C$5*D5+$C$6*D6+$C$7*D7+$C$8*D8+$C$9*D9+$C$10*D10+$C$11*D11+$C$12*D12+$C$13*D13+$C$14*D14+$C$15*D15+$C$16*D16+$C$17*D17+$C$18*D18+$C$19*D19+$C$20*D20+$C$21*D21+$C$22*D22+$C$23*D23+$C$24*D24+$C$25*D25+$C$26*D26+$C$27*D27+$C$28*D28+$C$29*D29+$C$30*D30+$C$31*D31+$C$32*D32+$C$33*D33 -> 3158520 | E34: =$C$5*E5+$C$6*E6+$C$7*E7+$C$8*E8+$C$9*E9+$C$10*E10+$C$11*E11+$C$12*E12+$C$13*E13+$C$14*E14+$C$15*E15+$C$16*E16+$C$17*E17+$C$18*E18+$C$19*E19+$C$20*E20+$C$21*E21+$C$22*E22+$C$23*E23+$C$24*E24+$C$25*E25+$C$26*E26+$C$27*E27+$C$28*E28+$C$29*E29+$C$30*E30+$C$31*E31+$C$32*E32+$C$33*E33 -> 2633310 | F34: =$C$5*F5+$C$6*F6+$C$7*F7+$C$8*F8+$C$9*F9+$C$10*F10+$C$11*F11+$C$12*F12+$C$13*F13+$C$14*F14+$C$15*F15+$C$16*F16+$C$17*F17+$C$18*F18+$C$19*F19+$C$20*F20+$C$21*F21+$C$22*F22+$C$23*F23+$C$24*F24+$C$25*F25+$C$26*F26+$C$27*F27+$C$28*F28+$C$29*F29+$C$30*F30+$C$31*F31+$C$32*F32+$C$33*F33 -> 2077710 | G34: =$C$5*G5+$C$6*G6+$C$7*G7+$C$8*G8+$C$9*G9+$C$10*G10+$C$11*G11+$C$12*G12+$C$13*G13+$C$14*G14+$C$15*G15+$C$16*G16+$C$17*G17+$C$18*G18+$C$19*G19+$C$20*G20+$C$21*G21+$C$22*G22+$C$23*G23+$C$24*G24+$C$25*G25+$C$26*G26+$C$27*G27+$C$28*G28+$C$29*G29+$C$30*G30+$C$31*G31+$C$32*G32+$C$33*G33 -> 659310 | H34: =$C$5*H5+$C$6*H6+$C$7*H7+$C$8*H8+$C$9*H9+$C$10*H10+$C$11*H11+$C$12*H12+$C$13*H13+$C$14*H14+$C$15*H15+$C$16*H16+$C$17*H17+$C$18*H18+$C$19*H19+$C$20*H20+$C$21*H21+$C$22*H22+$C$23*H23+$C$24*H24+$C$25*H25+$C$26*H26+$C$27*H27+$C$28*H28+$C$29*H29+$C$30*H30+$C$31*H31+$C$32*H32+$C$33*H33 -> 3072960 | I34: =$C$5*I5+$C$6*I6+$C$7*I7+$C$8*I8+$C$9*I9+$C$10*I10+$C$11*I11+$C$12*I12+$C$13*I13+$C$14*I14+$C$15*I15+$C$16*I16+$C$17*I17+$C$18*I18+$C$19*I19+$C$20*I20+$C$21*I21+$C$22*I22+$C$23*I23+$C$24*I24+$C$25*I25+$C$26*I26+$C$27*I27+$C$28*I28+$C$29*I29+$C$30*I30+$C$31*I31+$C$32*I32+$C$33*I33 -> 1501320 | J34: =$C$5*J5+$C$6*J6+$C$7*J7+$C$8*J8+$C$9*J9+$C$10*J10+$C$11*J11+$C$12*J12+$C$13*J13+$C$14*J14+$C$15*J15+$C$16*J16+$C$17*J17+$C$18*J18+$C$19*J19+$C$20*J20+$C$21*J21+$C$22*J22+$C$23*J23+$C$24*J24+$C$25*J25+$C$26*J26+$C$27*J27+$C$28*J28+$C$29*J29+$C$30*J30+$C$31*J31+$C$32*J32+$C$33*J33 -> 2581380 | K34: =$C$5*K5+$C$6*K6+$C$7*K7+$C$8*K8+$C$9*K9+$C$10*K10+$C$11*K11+$C$12*K12+$C$13*K13+$C$14*K14+$C$15*K15+$C$16*K16+$C$17*K17+$C$18*K18+$C$19*K19+$C$20*K20+$C$21*K21+$C$22*K22+$C$23*K23+$C$24*K24+$C$25*K25+$C$26*K26+$C$27*K27+$C$28*K28+$C$29*K29+$C$30*K30+$C$31*K31+$C$32*K32+$C$33*K33 -> 1769850 | ... T34: =$C$5*T5+$C$6*T6+$C$7*T7+$C$8*T8+$C$9*T9+$C$10*T10+$C$11*T11+$C$12*T12+$C$13*T13+$C$14*T14+$C$15*T15+$C$16*T16+$C$17*T17+$C$18*T18+$C$19*T19+$C$20*T20+$C$21*T21+$C$22*T22+$C$23*T23+$C$24*T24+$C$25*T25+$C$26*T26+$C$27*T27+$C$28*T28+$C$29*T29+$C$30*T30+$C$31*T31+$C$32*T32+$C$33*T33 -> 35782020
A35: =SUM(A4:A34) -> 0 | B35: Promedio de Trabajadores | D35: =SUM(D5:D33) -> 372 | E35: =SUM(E5:E33) -> 309 | F35: =SUM(F5:F33) -> 235 | G35: =SUM(G5:G33) -> 56 | H35: =SUM(H5:H33) -> 364 | I35: =SUM(I5:I33) -> 173 | J35: =SUM(J5:J33) -> 321 | K35: =SUM(K5:K33) -> 211 | ... T35: =SUM(T5:T33) -> 4208
B36: Salario Agosto-Diciembre | D36: =D34*5/1000 -> 15792.6 | E36: =E34*5/1000 -> 13166.55 | F36: =F34*5/1000 -> 10388.55 | G36: =G34*5/1000 -> 3296.55 | H36: =H34*5/1000 -> 15364.8 | I36: =I34*5/1000 -> 7506.6 | J36: =J34*5/1000 -> 12906.9 | K36: =K34*5/1000 -> 8849.25 | ... T36: =T34*5/1000 -> 178910.1 | U36: =SUM(T36:T36,T39) -> 252510.25
B37: Pago 10 USD | T37: =T35*120/1000*5 -> 2524.8
B38: Salario Julio | D38: 1341.65 | E38: 955.7 | F38: 1232.13 | G38: 163.72 | H38: 768.07 | I38: 1251 | J38: 877.95 | K38: 840.92 | L38: 535.61 | M38: 407.37 | N38: 734.39 | O38: 504.87 | P38: 1116.29 | Q38: 609.72 | R38: 582.98 | S38: 533.49 | T38: =SUM(D38:S38) -> 12455.86
B39: Salario Enero - Junio | D39: ='EMPLEO Y SALARIO'!L7 -> 4957.56 | E39: ='EMPLEO Y SALARIO'!L8 -> 5962.61 | F39: ='EMPLEO Y SALARIO'!L10 -> 7884.9 | G39: ='EMPLEO Y SALARIO'!L9 -> 1082.72 | H39: ='EMPLEO Y SALARIO'!L11 -> 4030.59 | I39: ='EMPLEO Y SALARIO'!L12 -> 3687.79 | J39: ='EMPLEO Y SALARIO'!L13 -> 4853.17 | K39: ='EMPLEO Y SALARIO'!L14 -> 4825.82 | L39: ='EMPLEO Y SALARIO'!L15 -> 3304.66 | M39: ='EMPLEO Y SALARIO'!L16 -> 3178.18 | N39: ='EMPLEO Y SALARIO'!L17 -> 4258.48 | O39: ='EMPLEO Y SALARIO'!L18 -> 3081.3 | P39: ='EMPLEO Y SALARIO'!L19 -> 11651.85 | Q39: ='EMPLEO Y SALARIO'!L20 -> 3685.09 | R39: ='EMPLEO Y SALARIO'!L21 -> 3829.86 | S39: ='EMPLEO Y SALARIO'!L22 -> 3325.57 | T39: =SUM(D39:S39) -> 73600.15
B40: Fondo Salario | D40: =SUM(D36:D39) -> 22091.81 | E40: =SUM(E36:E39) -> 20084.86 | F40: =SUM(F36:F39) -> 19505.58 | G40: =SUM(G36:G39) -> 4542.99 | H40: =SUM(H36:H39) -> 20163.46 | I40: =SUM(I36:I39) -> 12445.39 | J40: =SUM(J36:J39) -> 18638.02 | K40: =SUM(K36:K39) -> 14515.99 | ... S40: =SUM(S36:S39) -> 13044.01 | T40: =SUM(D40:S40) -> 264966.11
B41: Gasto salario/Ingreso Total | D41: =D40/'EMPLEO Y SALARIO'!D7 -> 0.1608213 | E41: =E40/'EMPLEO Y SALARIO'!D8 -> 0.075793652 | F41: =F40/'EMPLEO Y SALARIO'!D10 -> 0.0679368 | G41: =G40/'EMPLEO Y SALARIO'!D9 -> 0.12100146 | H41: =H40/'EMPLEO Y SALARIO'!D11 -> 0.18114681 | I41: =I40/'EMPLEO Y SALARIO'!D12 -> 0.091128226 | J41: =J40/'EMPLEO Y SALARIO'!D13 -> 0.36839354 | K41: =K40/'EMPLEO Y SALARIO'!D14 -> 0.12827999 | L41: =L40/'EMPLEO Y SALARIO'!D15 -> 0.14346779 | M41: =M40/'EMPLEO Y SALARIO'!D16 -> 0.26833003 | N41: =N40/'EMPLEO Y SALARIO'!D17 -> 0.095059411 | O41: =O40/'EMPLEO Y SALARIO'!D18 -> 0.28876186 | P41: =P40/'EMPLEO Y SALARIO'!D19 -> 0.16760996 | Q41: =Q40/'EMPLEO Y SALARIO'!D20 -> 0.15009006 | R41: =R40/'EMPLEO Y SALARIO'!D21 -> 0.14848153 | S41: =S40/'EMPLEO Y SALARIO'!D22 -> 0.27567974 | T41: =T40/'EMPLEO Y SALARIO'!D23 -> 0.13472085
B44: Fondo Salario 2026 | D44: =D34*12/1000 -> 37902.24 | E44: =E34*12/1000 -> 31599.72 | F44: =F34*12/1000 -> 24932.52 | G44: =G34*12/1000 -> 7911.72 | H44: =H34*12/1000 -> 36875.52 | I44: =I34*12/1000 -> 18015.84 | J44: =J34*12/1000 -> 30976.56 | K44: =K34*12/1000 -> 21238.2 | ... T44: =T34*12/1000 -> 429384.24
D45: =1200*12*D35/1000 -> 5356.8 | E45: =1200*12*E35/1000 -> 4449.6 | F45: =1200*12*F35/1000 -> 3384 | G45: =1200*12*G35/1000 -> 806.4 | H45: =1200*12*H35/1000 -> 5241.6 | I45: =1200*12*I35/1000 -> 2491.2 | J45: =1200*12*J35/1000 -> 4622.4 | K45: =1200*12*K35/1000 -> 3038.4 | ... T45: =1200*12*T35/1000 -> 60595.2
D46: =SUM(D44:D44) -> 37902.24 | E46: =SUM(E44:E44) -> 31599.72 | F46: =SUM(F44:F44) -> 24932.52 | G46: =SUM(G44:G44) -> 7911.72 | H46: =SUM(H44:H44) -> 36875.52 | I46: =SUM(I44:I44) -> 18015.84 | J46: =SUM(J44:J44) -> 30976.56 | K46: =SUM(K44:K44) -> 21238.2 | ... T46: =SUM(T44:T44) -> 429384.24
C48: =C39+C36+C38 -> 0 | D48: =D39+D36+D38 -> 22091.81 | E48: =E39+E36+E38 -> 20084.86 | F48: =F39+F36+F38 -> 19505.58 | G48: =G39+G36+G38 -> 4542.99 | H48: =H39+H36+H38 -> 20163.46 | I48: =I39+I36+I38 -> 12445.39 | J48: =J39+J36+J38 -> 18638.02 | ... T48: =T39+T36+T38 -> 264966.11
D49: =D48*0.3 -> 6627.543 | E49: =E48*0.3 -> 6025.458 | F49: =F48*0.3 -> 5851.674 | G49: =G48*0.3 -> 1362.897 | H49: =H48*0.3 -> 6049.038 | I49: =I48*0.3 -> 3733.617 | J49: =J48*0.3 -> 5591.406 | K49: =K48*0.3 -> 4354.797 | ... T49: =T48*0.3 -> 79489.833
D50: =D35*1200*12/1000 -> 5356.8 | E50: =E35*1200*12/1000 -> 4449.6 | F50: =F35*1200*12/1000 -> 3384 | G50: =G35*1200*12/1000 -> 806.4 | H50: =H35*1200*12/1000 -> 5241.6 | I50: =I35*1200*12/1000 -> 2491.2 | J50: =J35*1200*12/1000 -> 4622.4 | K50: =K35*1200*12/1000 -> 3038.4 | ... T50: =T35*1200*12/1000 -> 60595.2
D53: =SUM(D48:D49) -> 28719.353 | E53: =SUM(E48:E49) -> 26110.318 | F53: =SUM(F48:F49) -> 25357.254 | G53: =SUM(G48:G49) -> 5905.887 | H53: =SUM(H48:H49) -> 26212.498 | I53: =SUM(I48:I49) -> 16179.007 | J53: =SUM(J48:J49) -> 24229.426 | K53: =SUM(K48:K49) -> 18870.787 | ... T53: =SUM(T48:T49) -> 344455.94

Sheet MODELO PLAN 
J1: 1.491
A2: TABLA RESULMEN DE LOS INDICADORES FUNDAMENTALES DEL PLAN 2026. | F2: =750/120 -> 6.25 | G2: NOTA: NO MODIFICAR LAS CELDAS CON FORMULAS
A3: Entidad: OSDE CAMPISMO POPULAR | H3: =H52-H4 -> 129885.25 | J3: =J52-J4 -> 101867.49
H4: =H52*5% -> 6836.0656 | J4: =J52*5% -> 5361.447
A5: Indicadores | B5: UM | C5: Real 2024 | D5: I Semestre 2025 | G5: Año 2025 | J5: Plan 2026
D7: Plan | E7: Real | F7: % | G7: Plan | H7: Estimado | I7: % | K7: EST 2025 / REAL 2024 | L7: PLAN 2026 /REAL 2024 | M7: PLAN 2026 /EST 2025
A8: NIVELES DE ACTIVIDAD
A9: Visitantes | B9: Miles
A10: Turistas Extranjeros Fisicos | B10: Miles | C10: =C27+C38 -> 3.043 | D10: =D27+D38 -> 2.692 | E10: =E27+E38 -> 1.097 | F10: =E10/D10 -> 0.40750371 | G10: =G27+G38 -> 6 | H10: =H27+H38 -> 5.4 | I10: =H10/G10 -> 0.9 | J10: =J27+J38 -> 5.9 | K10: =H10/C10 -> 1.7745646 | L10: =J10/C10 -> 1.9388761 | M10: =J10/H10 -> 1.0925926
A11: Estancia Promedio | B11: Dias | C11: =C28+C39 -> 2.9086428 | D11: =D28+D39 -> 2.1846211 | E11: =E28+E39 -> 2.6645397 | F11: =E11/D11 -> 1.2196805 | G11: =G28+G39 -> 2.1816667 | H11: =H28+H39 -> 1.195 | I11: =H11/G11 -> 0.54774637 | J11: =J28+J39 -> 1.159322 | K11: =H11/C11 -> 0.41084454 | L11: =J11/C11 -> 0.39857835 | M11: =J11/H11 -> 0.97014396
A12: Turistas días extranjeros | B12: Miles | C12: =C29+C40 -> 8.851 | D12: =D29+D40 -> 5.881 | E12: =E29+E40 -> 2.923 | F12: =E12/D12 -> 0.49702432 | G12: =G29+G40 -> 13.09 | H12: =H29+H40 -> 6.453 | I12: =H12/G12 -> 0.49297173 | J12: =J29+J40 -> 6.84 | K12: =H12/C12 -> 0.72907016 | L12: =J12/C12 -> 0.77279403 | M12: =J12/H12 -> 1.0599721
A13: Turistas días nacionales | B13: Miles | C13: =C30+C41 -> 1733.042 | D13: =D30+D41 -> 815.092 | E13: =E30+E41 -> 698.545 | F13: =E13/D13 -> 0.85701369 | G13: =G30+G41 -> 1982.6 | H13: =H30+H41 -> 1982.6 | I13: =H13/G13 -> 1 | J13: =J30+J41 -> 2000 | K13: =H13/C13 -> 1.144 | L13: =J13/C13 -> 1.1540401 | M13: =J13/H13 -> 1.0087764
A14: Turistas días totales | B14: Miles | C14: =C12+C13 -> 1741.893 | D14: =D12+D13 -> 820.973 | E14: =E12+E13 -> 701.468 | F14: =E14/D14 -> 0.85443492 | G14: =G12+G13 -> 1995.69 | H14: =H12+H13 -> 1989.053 | I14: =H14/G14 -> 0.99667433 | J14: =J12+J13 -> 2006.84 | K14: =H14/C14 -> 1.1418916 | L14: =J14/C14 -> 1.1521029 | M14: =J14/H14 -> 1.0089424
A15: Ingresos turísticos | B15: MMCUP | C15: =C32+C43 -> 1735.074 | D15: =D32+D43 -> 774.01167 | E15: =E32+E43 -> 952.63389 | F15: =E15/D15 -> 1.2307746 | G15: =G32+G43 -> 1796.9 | H15: =H32+H43 -> 1800 | I15: =H15/G15 -> 1.0017252 | J15: =J32+J43 -> 1826.5 | K15: =H15/C15 -> 1.0374197 | L15: =J15/C15 -> 1.0526929 | M15: =J15/H15 -> 1.0147222
A16: de ellos: Alojamiento | B16: MMCUP | C16: =C33+C44 -> 89.447 | D16: =D33+D44 -> 79.472883 | E16: =E33+E44 -> 39.28811 | F16: =E16/D16 -> 0.49435869 | G16: =G33+G44 -> 211.70284 | H16: =H33+H44 -> 156.3 | I16: =H16/G16 -> 0.73829902 | J16: =J33+J44 -> 157.863 | K16: =H16/C16 -> 1.7474035 | L16: =J16/C16 -> 1.7648775 | M16: =J16/H16 -> 1.01
A17: Exportaciones de Servicios | B17: MMUSD | C17: =C34+C45 -> 0.3997 | D17: =D34+D45 -> 0.28530412 | E17: =E34+E45 -> 0.19992042 | F17: =E17/D17 -> 0.7007274 | G17: =G34+G45 -> 0.73 | H17: =H34+H45 -> 0.484 | I17: =H17/G17 -> 0.6630137 | J17: =J34+J45 -> 0.533 | K17: =H17/C17 -> 1.2109082 | L17: =J17/C17 -> 1.3335001 | M17: =J17/H17 -> 1.1012397
A18: Ingreso por turistas días Totales | B18: CUP | C18: =C15*1000/C14 -> 996.08529 | D18: =D15*1000/D14 -> 942.79796 | E18: =E15*1000/E14 -> 1358.0575 | F18: =E18/D18 -> 1.4404544 | G18: =G15*1000/(G12+G13) -> 900.39034 | H18: =H15*1000/(H12+H13) -> 904.95326 | I18: =H18/G18 -> 1.0050677 | J18: =J15*1000/(J12+J13) -> 910.13733 | K18: =H18/C18 -> 0.90850981 | L18: =J18/C18 -> 0.91371425 | M18: =J18/H18 -> 1.0057285
A19: Exportaciones por turistas días Extranjeros | B19: USD | C19: =C17*1000/C12 -> 45.158739 | D19: =D17*1000/D12 -> 48.512859 | E19: =E17*1000/E12 -> 68.395627 | F19: =E19/D19 -> 1.4098453 | G19: =G17*1000/G12 -> 55.767762 | H19: =H17*1000/H12 -> 75.003874 | I19: =H19/G19 -> 1.3449325 | J19: =J17*1000/J12 -> 77.923977 | K19: =H19/C19 -> 1.6608939 | L19: =J19/C19 -> 1.725557 | M19: =J19/H19 -> 1.0389327
A20: Habitaciones días existentes | B20: Miles | C20: =C23*366 -> 1630.53 | D20: ='[7]Modelo 1'!J65 -> 806355 | E20: ='[7]Modelo 1'!K65 -> 806355 | F20: =E20/D20 -> 1 | G20: =4455*365/1000 -> 1626.075 | H20: =4455*365/1000 -> 1626.075 | I20: =H20/G20 -> 1 | J20: =J23*365 -> 1626.075 | K20: =H20/C20 -> 0.99726776 | L20: =J20/C20 -> 0.99726776 | M20: =J20/H20 -> 1
A21: Habitaciones días ocupadas | B21: Miles | C21: 280.115 | D21: ='[7]Modelo 1'!J66 -> 145693 | E21: ='[7]Modelo 1'!K66 -> 116532 | F21: =E21/D21 -> 0.79984625 | G21: 340.5 | H21: 340.5 | I21: =H21/G21 -> 1 | J21: =J24*365*38% -> 367.555 | K21: =H21/C21 -> 1.2155722 | L21: =J21/C21 -> 1.3121575 | M21: =J21/H21 -> 1.0794567
A22: Ocupación | B22: % | C22: =C21/C20*100 -> 17.179383 | D22: =D21/D20*100 -> 18.068097 | E22: =E21/E20*100 -> 14.451699 | F22: =E22/D22 -> 0.79984625 | G22: =G21/G20*100 -> 20.939994 | H22: =H21/H20*100 -> 20.939994 | I22: =H22/G22 -> 1 | J22: =J21/J20*100 -> 22.603816 | K22: =H22/C22 -> 1.2189025 | L22: =J22/C22 -> 1.3157525 | M22: =J22/H22 -> 1.0794567
A23: Habitaciones existentes | B23: Miles | C23: 4.455 | D23: ='[7]HABITACIONES DIAS '!L28/1000 -> 4.455 | E23: ='[7]HABITACIONES DIAS '!M28/1000 -> 4.455 | F23: =E23/D23 -> 1 | G23: 4.455 | H23: 4.455 | I23: =H23/G23 -> 1 | J23: 4.455 | K23: =H23/C23 -> 1 | L23: =J23/C23 -> 1 | M23: =J23/H23 -> 1
A24: Habitaciones disponibles | B24: Miles | C24: 2.541 | D24: ='[7]HABITACIONES DIAS '!O28/1000 -> 2.592 | E24: ='[7]HABITACIONES DIAS '!P28/1000 -> 2.4667 | F24: =E24/D24 -> 0.95165895 | G24: 2.62 | H24: 2.62 | I24: =H24/G24 -> 1 | J24: 2.65 | K24: =H24/C24 -> 1.0310901 | L24: =J24/C24 -> 1.0428965 | M24: =J24/H24 -> 1.0114504
A25: Habitaciones fuera de orden | B25: Miles | C25: =C23-C24 -> 1.914 | D25: =D23-D24 -> 1.863 | E25: =E23-E24 -> 1.9883 | F25: =E25/D25 -> 1.0672571 | G25: =G23-G24 -> 1.835 | H25: =H23-H24 -> 1.835 | I25: =H25/G25 -> 1 | J25: =J23-J24 -> 1.805 | K25: =H25/C25 -> 0.95872518 | L25: =J25/C25 -> 0.9430512 | M25: =J25/H25 -> 0.98365123
A26: NIVELES DE ACTIVIDAD (SECTOR ESTATAL)
A27: Turistas Extranjeros Fisicos | B27: Miles | C27: 3.043 | D27: ='[7]Modelo 1'!J70/1000 -> 2.692 | E27: ='[7]Modelo 1'!K70/1000 -> 1.097 | F27: =E27/D27 -> 0.40750371 | G27: 6 | H27: 5.4 | I27: =H27/G27 -> 0.9 | J27: 5.9 | K27: =H27/C27 -> 1.7745646 | L27: =J27/C27 -> 1.9388761 | M27: =J27/H27 -> 1.0925926
A28: Estancia Promedio | B28: Dias | C28: =C29/C27 -> 2.9086428 | D28: =D29/D27 -> 2.1846211 | E28: =E29/E27 -> 2.6645397 | F28: =E28/D28 -> 1.2196805 | G28: =G29/G27 -> 2.1816667 | H28: =H29/H27 -> 1.195 | I28: =H28/G28 -> 0.54774637 | J28: =J29/J27 -> 1.159322 | K28: =H28/C28 -> 0.41084454 | L28: =J28/C28 -> 0.39857835 | M28: =J28/H28 -> 0.97014396
A29: Turistas días extranjeros | B29: Miles | C29: 8.851 | D29: ='[7]Modelo 1'!J62/1000 -> 5.881 | E29: ='[7]Modelo 1'!K62/1000 -> 2.923 | F29: =E29/D29 -> 0.49702432 | G29: 13.09 | H29: 6.453 | I29: =H29/G29 -> 0.49297173 | J29: 6.84 | K29: =H29/C29 -> 0.72907016 | L29: =J29/C29 -> 0.77279403 | M29: =J29/H29 -> 1.0599721
A30: Turistas días nacionales | B30: Miles | C30: 1733.042 | D30: ='[7]Modelo 1'!J63/1000 -> 815.092 | E30: ='[7]Modelo 1'!K63/1000 -> 698.545 | F30: =E30/D30 -> 0.85701369 | G30: 1982.6 | H30: 1982.6 | I30: =H30/G30 -> 1 | J30: 2000 | K30: =H30/C30 -> 1.144 | L30: =J30/C30 -> 1.1540401 | M30: =J30/H30 -> 1.0087764
A31: Turistas días totales | B31: Miles | C31: =C29+C30 -> 1741.893 | D31: =D29+D30 -> 820.973 | E31: =E29+E30 -> 701.468 | F31: =E31/D31 -> 0.85443492 | G31: =G29+G30 -> 1995.69 | H31: =H29+H30 -> 1989.053 | I31: =H31/G31 -> 0.99667433 | J31: =J29+J30 -> 2006.84 | K31: =H31/C31 -> 1.1418916 | L31: =J31/C31 -> 1.1521029 | M31: =J31/H31 -> 1.0089424
A32: Ingresos turísticos | B32: MMCUP | C32: 1735.074 | D32: ='[7]Modelo 1'!J10/1000 -> 774.01167 | E32: ='[7]Modelo 1'!K10/1000 -> 952.63389 | F32: =E32/D32 -> 1.2307746 | G32: 1796.9 | H32: 1800 | I32: =H32/G32 -> 1.0017252 | J32: 1826.5 | K32: =H32/C32 -> 1.0374197 | L32: =J32/C32 -> 1.0526929 | M32: =J32/H32 -> 1.0147222
A33: de ellos: Alojamiento | B33: MMCUP | C33: 89.447 | D33: ='[7]Modelo 1'!J12/1000 -> 79.472883 | E33: ='[7]Modelo 1'!K12/1000 -> 39.28811 | F33: =E33/D33 -> 0.49435869 | G33: 211.70284 | H33: 156.3 | I33: =H33/G33 -> 0.73829902 | J33: =H33*101% -> 157.863 | K33: =H33/C33 -> 1.7474035 | L33: =J33/C33 -> 1.7648775 | M33: =J33/H33 -> 1.01
A34: Exportaciones de Servicios | B34: MMUSD | C34: 0.3997 | D34: ='[7]Modelo 1'!J26/120/1000 -> 0.28530412 | E34: ='[7]Modelo 1'!K26/120/1000 -> 0.19992042 | F34: =E34/D34 -> 0.7007274 | G34: =G79 -> 0.73 | H34: 0.484 | I34: =H34/G34 -> 0.6630137 | J34: 0.533 | K34: =H34/C34 -> 1.2109082 | L34: =J34/C34 -> 1.3335001 | M34: =J34/H34 -> 1.1012397
A35: Ingreso por turistas días Totales | B35: CUP | C35: =C32*1000/C31 -> 996.08529 | D35: =D32*1000/D31 -> 942.79796 | E35: =E32*1000/E31 -> 1358.0575 | F35: =E35/D35 -> 1.4404544 | G35: =G32*1000/G31 -> 900.39034 | H35: =H32*1000/H31 -> 904.95326 | I35: =H35/G35 -> 1.0050677 | J35: =J32*1000/J31 -> 910.13733 | K35: =H35/C35 -> 0.90850981 | L35: =J35/C35 -> 0.91371425 | M35: =J35/H35 -> 1.0057285
A36: Exportaciones por turistas días Extranjeros | B36: USD | C36: =C34*1000/C29 -> 45.158739 | D36: =D34*1000/D29 -> 48.512859 | E36: =E34*1000/E29 -> 68.395627 | F36: =E36/D36 -> 1.4098453 | G36: =G34*1000/G29 -> 55.767762 | H36: =H34*1000/H29 -> 75.003874 | I36: =H36/G36 -> 1.3449325 | J36: =J34*1000/J29 -> 77.923977 | K36: =H36/C36 -> 1.6608939 | L36: =J36/C36 -> 1.725557 | M36: =J36/H36 -> 1.0389327
A37: NIVELES DE ACTIVIDAD (AEI) | F37: =E37/D37 -> #DIV/0! | I37: =H37/G37 -> #DIV/0!
A38: Turistas Extranjeros Fisicos | B38: Miles | F38: =E38/D38 -> #DIV/0! | I38: =H38/G38 -> #DIV/0! | K38: =H38/C38 -> #DIV/0! | L38: =H38/A38*100 -> #VALUE! | M38: =J38/H38 -> #DIV/0!
A39: Estancia Promedio | B39: Dias | F39: =E39/D39 -> #DIV/0! | I39: =H39/G39 -> #DIV/0! | K39: =H39/C39 -> #DIV/0! | L39: =H39/A39*100 -> #VALUE! | M39: =J39/H39 -> #DIV/0!
A40: Turistas días extranjeros | B40: Miles | F40: =E40/D40 -> #DIV/0! | I40: =H40/G40 -> #DIV/0! | K40: =H40/C40 -> #DIV/0! | L40: =H40/A40*100 -> #VALUE! | M40: =J40/H40 -> #DIV/0!
A41: Turistas días nacionales | B41: Miles | F41: =E41/D41 -> #DIV/0! | I41: =H41/G41 -> #DIV/0! | K41: =H41/C41 -> #DIV/0! | L41: =H41/A41*100 -> #VALUE! | M41: =J41/H41 -> #DIV/0!
A42: Turistas días totales | B42: Miles | C42: =C40+C41 -> 0 | F42: =E42/D42 -> #DIV/0! | G42: =G40+G41 -> 0 | H42: =H40+H41 -> 0 | I42: =H42/G42 -> #DIV/0! | J42: =J40+J41 -> 0 | K42: =H42/C42 -> #DIV/0! | L42: =H42/A42*100 -> #VALUE! | M42: =J42/H42 -> #DIV/0!
A43: Ingresos turísticos | B43: MMCUP | F43: =E43/D43 -> #DIV/0! | I43: =H43/G43 -> #DIV/0! | K43: =H43/C43 -> #DIV/0! | L43: =H43/A43*100 -> #VALUE! | M43: =J43/H43 -> #DIV/0!
A44: de ellos: Alojamiento | B44: MMCUP | F44: =E44/D44 -> #DIV/0! | I44: =H44/G44 -> #DIV/0! | K44: =H44/C44 -> #DIV/0! | L44: =H44/A44*100 -> #VALUE! | M44: =J44/H44 -> #DIV/0!
A45: Exportaciones de Servicios | B45: MMUSD | F45: =E45/D45 -> #DIV/0! | I45: =H45/G45 -> #DIV/0! | K45: =H45/C45 -> #DIV/0! | L45: =H45/A45*100 -> #VALUE! | M45: =J45/H45 -> #DIV/0!
A46: Ingreso por turistas días Totales | B46: CUP | C46: =C43*1000/C42 -> #DIV/0! | F46: =E46/D46 -> #DIV/0! | G46: =G43*1000/G42 -> #DIV/0! | H46: =H43*1000/H42 -> #DIV/0! | I46: =H46/G46 -> #DIV/0! | J46: =J43*1000/J42 -> #DIV/0! | K46: =H46/C46 -> #DIV/0! | L46: =H46/A46*100 -> #DIV/0! | M46: =J46/H46 -> #DIV/0!
A47: Exportaciones por turistas días Extranjeros | B47: USD | C47: =C45*1000/C40 -> #DIV/0! | F47: =E47/D47 -> #DIV/0! | G47: =G45*1000/G40 -> #DIV/0! | H47: =H45*1000/H40 -> #DIV/0! | I47: =H47/G47 -> #DIV/0! | J47: =J45*1000/J40 -> #DIV/0! | K47: =H47/C47 -> #DIV/0! | L47: =H47/A47*100 -> #DIV/0! | M47: =J47/H47 -> #DIV/0!
A48: INDICADORES DE EFICIENCIA
A49: Sector estatal
A50: Ingresos Totales | B50: MP | C50: 1801610.4 | D50: ='[7]Modelo 1'!J9 -> 794548.84 | E50: ='[7]Modelo 1'!K9 -> 973208.86 | F50: =E50/D50 -> 1.2248572 | G50: 1844302.9 | H50: 1850602.3 | I50: =H50/G50 -> 1.0034156 | J50: =H50*103.5% -> 1915373.4 | K50: =H50/C50 -> 1.0271934 | L50: =J50/C50 -> 1.0631452 | M50: =J50/H50 -> 1.035
A51: Costos y Gastos Totales | B51: MP | C51: 1669649.3 | D51: ='[7]Modelo 1'!J33 -> 747371.52 | E51: ='[7]Modelo 1'!K33 -> 883088.24 | F51: =E51/D51 -> 1.181592 | G51: 1688682.8 | H51: 1713881 | I51: =H51/G51 -> 1.0149218 | J51: =H51*105.5% -> 1808144.4 | K51: =H51/C51 -> 1.0264916 | L51: =J51/C51 -> 1.0829486 | M51: =J51/H51 -> 1.055 | N51: =H52*5% -> 6836.0656 | P51: =J52*5% -> 5361.447
A52: Utilidad antes del Impuesto | B52: MP | C52: =C50-C51 -> 131961.1 | D52: =D50-D51 -> 47177.315 | E52: =E50-E51 -> 90120.62 | F52: =E52/D52 -> 1.9102533 | G52: =G50-G51 -> 155620.04 | H52: =H50-H51 -> 136721.31 | I52: =H52/G52 -> 0.8785585 | J52: =J50-J51 -> 107228.94 | K52: =H52/C52 -> 1.0360729 | L52: =J52/C52 -> 0.81257991 | M52: =J52/H52 -> 0.7842884 | N52: =H52-N51 -> 129885.25 | P52: =J52-P51 -> 101867.49
A53: Gasto total por peso de Ingreso total | B53: Peso | C53: =C51/C50 -> 0.92675381 | D53: =D51/D50 -> 0.94062377 | E53: =E51/E50 -> 0.90739848 | F53: =E53/D53 -> 0.96467739 | G53: =G51/G50 -> 0.91562121 | H53: =H51/H50 -> 0.92612064 | I53: =H53/G53 -> 1.011467 | J53: =J51/J50 -> 0.94401669 | K53: =H53/C53 -> 0.99931679 | L53: =J53/C53 -> 1.0186273 | M53: =J53/H53 -> 1.0193237 | N53: =N52*35% -> 45459.837 | P53: =P52*35% -> 35653.622
A54: AEI | F54: =E54/D54 -> #DIV/0! | I54: =H54/G54 -> #DIV/0!
A55: Ingresos Totales | B55: MP | F55: =E55/D55 -> #DIV/0! | I55: =H55/G55 -> #DIV/0! | K55: =H55/C55 -> #DIV/0! | L55: =H55/A55*100 -> #VALUE! | M55: =J55/H55 -> #DIV/0!
A56: Costos y Gastos Totales | B56: MP | F56: =E56/D56 -> #DIV/0! | I56: =H56/G56 -> #DIV/0! | K56: =H56/C56 -> #DIV/0! | L56: =H56/A56*100 -> #VALUE! | M56: =J56/H56 -> #DIV/0!
A57: Utilidad antes del Impuesto | B57: MP | C57: =C55-C56 -> 0 | F57: =E57/D57 -> #DIV/0! | G57: =G55-G56 -> 0 | H57: =H55-H56 -> 0 | I57: =H57/G57 -> #DIV/0! | J57: =J55-J56 -> 0 | K57: =H57/C57 -> #DIV/0! | L57: =H57/A57*100 -> #VALUE! | M57: =J57/H57 -> #DIV/0!
A58: Gasto total por peso de Ingreso total | B58: Pesos | C58: =C56/C55 -> #DIV/0! | F58: =E58/D58 -> #DIV/0! | G58: =G56/G55 -> #DIV/0! | H58: =H56/H55 -> #DIV/0! | I58: =H58/G58 -> #DIV/0! | J58: =J56/J55 -> #DIV/0! | K58: =H58/C58 -> #DIV/0! | L58: =H58/A58*100 -> #DIV/0! | M58: =J58/H58 -> #DIV/0!
A59: INDICADORES DE EMPLEO Y SALARIO | N59: =N52-N53 -> 84425.411 | P59: =P52-P53 -> 66213.87
A60: Gasto de salario | B60: MP | C60: 161064.87 | D60: =[7]Modelo1B!J30 -> 115460.33 | E60: =[7]Modelo1B!K30 -> 73600.15 | F60: =E60/D60 -> 0.63744969 | G60: 264538.44 | H60: =G60*75% -> 198403.83 | I60: =H60/G60 -> 0.75 | J60: =H60*103% -> 204355.94 | K60: =H60/C60 -> 1.2318256 | L60: =J60/C60 -> 1.2687804 | M60: =J60/H60 -> 1.03 | N60: =N59*60% -> 50655.246 | P60: =P59*60% -> 39728.322
A61: Promedio de Trabajadores | B61: Uno | C61: 4289 | D61: ='[7]Modelo 1'!J56 -> 4950 | E61: ='[7]Modelo 1'!K56 -> 4276 | F61: =E61/D61 -> 0.86383838 | G61: 5200 | H61: 4726 | I61: =H61/G61 -> 0.90884615 | J61: 4900 | K61: =H61/C61 -> 1.1018886 | L61: =J61/C61 -> 1.1424574 | M61: =J61/H61 -> 1.0368176
A62: Salario Medio | B62: Pesos | C62: =C60*1000/C61/12 -> 3129.4177 | D62: =D60*1000/D61/6 -> 3887.5531 | E62: =E60*1000/E61/6 -> 2868.7305 | F62: =E62/D62 -> 0.73792702 | G62: =G60*1000/G61/12 -> 4239.398 | H62: =H60*1000/H61/12 -> 3498.4453 | I62: =H62/G62 -> 0.82522218 | J62: =J60*1000/J61/12 -> 3475.4412 | K62: =H62/C62 -> 1.1179221 | L62: =J62/C62 -> 1.1105712 | M62: =J62/H62 -> 0.99342449
A63: Indice de Gasto de salario por peso de ingreso total | B63: Pesos | C63: =C60/C50 -> 0.0894005 | D63: =D60/D50 -> 0.14531558 | E63: =E60/E50 -> 0.075626264 | F63: =E63/D63 -> 0.52042776 | G63: =G60/G50 -> 0.14343546 | H63: =H60/H50 -> 0.10721041 | I63: =H63/G63 -> 0.74744701 | J63: =J60/J50 -> 0.10669248 | K63: =H63/C63 -> 1.1992149 | L63: =J63/C63 -> 1.1934216 | M63: =J63/H63 -> 0.99516908
A64: Valor Agregado Bruto | B64: MP | C64: 519803.69 | D64: ='[7]EMPLEO Y SALARIO'!C23 -> 273020.07 | E64: ='[7]EMPLEO Y SALARIO'!D23 -> 287805.51 | F64: =E64/D64 -> 1.0541551 | G64: 671578.78 | H64: 673416.83 | I64: =H64/G64 -> 1.0027369 | J64: 690252.25 | K64: =H64/C64 -> 1.2955214 | L64: =J64/C64 -> 1.3279095 | M64: =J64/H64 -> 1.025
A65: Productividad a partir del VAB | B65: MP | C65: =C64/C61*1000/12 -> 10099.551 | D65: =D64/D61*1000/6 -> 9192.5949 | E65: =E64/E61*1000/6 -> 11217.864 | F65: =E65/D65 -> 1.2203152 | G65: =G64/G61*1000/12 -> 10762.48 | H65: =H64/H61*1000/12 -> 11874.327 | I65: =H65/G65 -> 1.1033076 | J65: =J64/J61*1000/12 -> 11738.984 | K65: =H65/C65 -> 1.1757282 | L65: =J65/C65 -> 1.1623273 | M65: =J65/H65 -> 0.98860204
A66: Aporte al RIE o pago de dividendos a los socios | B66: MP | C66: 51793.891 | D66: ='[7]Modelo 1'!J38 -> 8739.5976 | E66: ='[7]Modelo 1'!K38 -> 16694.845 | F66: =E66/D66 -> 1.9102533 | G66: 59509.733 | H66: =N60 -> 50655.246 | I66: =H66/G66 -> 0.85120945 | J66: =P60 -> 39728.322 | K66: =H66/C66 -> 0.97801585 | L66: =J66/C66 -> 0.76704648 | M66: =J66/H66 -> 0.7842884
A67: INDICADORES DE COMERCIO ELECTRONICO
A68: Ventas ONLINE | B68: MP | C68: 128884.2 | D68: ='[7]Modelo 1'!J46 -> 87859.111 | E68: ='[7]Modelo 1'!K46 -> 80713.4 | F68: =E68/D68 -> 0.91866853 | G68: 211702.84 | H68: =H69 -> 197354.1 | I68: =H68/G68 -> 0.93222227 | J68: =J69 -> 249288.5 | K68: =H68/C68 -> 1.5312513 | L68: =J68/C68 -> 1.9342053 | M68: =J68/H68 -> 1.2631534
A69: Cobros a traves de Pasarelas de Pagos y Canales Digitales | B69: MP | C69: 128884.2 | D69: ='[7]Modelo 1'!J47 -> 87859.111 | E69: ='[7]Modelo 1'!K47 -> 80713.4 | F69: =E69/D69 -> 0.91866853 | G69: 211702.84 | H69: =+H70+H71+H72+H73 -> 197354.1 | I69: =H69/G69 -> 0.93222227 | J69: =+J70+J71+J72+J73 -> 249288.5 | K69: =H69/C69 -> 1.5312513 | L69: =J69/C69 -> 1.9342053 | M69: =J69/H69 -> 1.2631534
A70: De ellos: Pos de Fincimex | B70: MP | C70: 10015.5 | D70: ='[7]Modelo 1'!J48 -> 17571.822 | E70: ='[7]Modelo 1'!K48 -> 7690 | F70: =E70/D70 -> 0.43763247 | G70: 42340.567 | H70: 10732.5 | I70: =H70/G70 -> 0.25348031 | J70: 10732.5 | K70: =H70/C70 -> 1.071589 | L70: =J70/C70 -> 1.071589 | M70: =J70/H70 -> 1
A71: Enzona | B71: MP | C71: 40705.7 | D71: ='[7]Modelo 1'!J49 -> 26357.733 | E71: ='[7]Modelo 1'!K49 -> 21538.2 | F71: =E71/D71 -> 0.81714918 | G71: 63510.851 | H71: 15356.4 | I71: =H71/G71 -> 0.24179175 | J71: 18581.244 | K71: =H71/C71 -> 0.37725429 | L71: =J71/C71 -> 0.45647769 | M71: =J71/H71 -> 1.21
A72: Transfermovil | B72: MP | C72: 58428 | D72: ='[7]Modelo 1'!J50 -> 26357.733 | E72: ='[7]Modelo 1'!K50 -> 43359.9 | F72: =E72/D72 -> 1.6450542 | G72: 63510.851 | H72: 162365.2 | I72: =H72/G72 -> 2.5564954 | J72: 211074.76 | K72: =H72/C72 -> 2.7788937 | L72: =J72/C72 -> 3.6125618 | M72: =J72/H72 -> 1.3
A73: Pasarelas | B73: MP | C73: 19735.1 | D73: ='[7]Modelo 1'!J51 -> 17571.822 | E73: ='[7]Modelo 1'!K51 -> 8125.3 | F73: =E73/D73 -> 0.46240509 | G73: 42340.567 | H73: 8900 | I73: =H73/G73 -> 0.2102003 | J73: 8900 | K73: =H73/C73 -> 0.45097314 | L73: =J73/C73 -> 0.45097314 | M73: =J73/H73 -> 1
A74: Ventas en MLC | B74: MP | C74: 399.7 | D74: ='[7]Modelo 1'!J52 -> 285.30412 | E74: ='[7]Modelo 1'!K52 -> 199.92042 | F74: =E74/D74 -> 0.7007274 | G74: 729.99833 | H74: =H34*1000 -> 484 | I74: =H74/G74 -> 0.66301521 | J74: =J79*1000 -> 533 | K74: =H74/C74 -> 1.2109082 | L74: =J74/C74 -> 1.3335001 | M74: =J74/H74 -> 1.1012397
A75: de ello: Ventas en MLC al Mercado Interno | B75: MP | C75: 399.7 | D75: ='[7]Modelo 1'!J53 -> 285.30412 | E75: ='[7]Modelo 1'!K53 -> 199.92042 | F75: =E75/D75 -> 0.7007274 | G75: 729 | H75: =H74 -> 484 | I75: =H75/G75 -> 0.66392318 | J75: =J81*1000 -> 533 | K75: =H75/C75 -> 1.2109082 | L75: =J75/C75 -> 1.3335001 | M75: =J75/H75 -> 1.1012397
A76: Pagos realizados a través de canales digitales | B76: MP | C76: 140322.4 | D76: ='[7]Modelo 1'!J54 -> 132305.69 | E76: ='[7]Modelo 1'!K54 -> 204709.8 | F76: =E76/D76 -> 1.5472487 | G76: 299269.9 | H76: 596358.35 | I76: =H76/G76 -> 1.9927108 | J76: 608285.51 | K76: =H76/C76 -> 4.2499155 | L76: =J76/C76 -> 4.3349138 | M76: =J76/H76 -> 1.02
A77: INDICADORES SECTOR EXTERNO
A78: Sector Estatal + AEI (DEL MODELO COMEX)
A79: Exportaciones de bienes y servicios | B79: MMUSD | C79: =+C80+C81 -> 0.38414 | D79: =+D80+D81 -> 285.30412 | E79: =+E80+E81 -> 199.92042 | F79: =E79/D79 -> 0.7007274 | G79: =+G80+G81 -> 0.73 | H79: =+H80+H81 -> 0.484 | I79: =H79/G79 -> 0.6630137 | J79: =+J80+J81 -> 0.533 | K79: =H79/C79 -> 1.2599573 | L79: =J79/C79 -> 1.387515 | M79: =J79/H79 -> 1.1012397
A80: Ingresos en divisa desde el exterior | B80: MMUSD | F80: =E80/D80 -> #DIV/0! | G80: 0.001 | I80: =H80/G80 -> 0 | K80: =H80/C80 -> #DIV/0! | L80: =J80/C80 -> #DIV/0! | M80: =J80/H80 -> #DIV/0!
A81: Ingresos en divisa captados en el país | B81: MMUSD | C81: =SUM(C82:C82) -> 0.38414 | D81: =SUM(D82:D82) -> 285.30412 | E81: =SUM(E82:E82) -> 199.92042 | F81: =E81/D81 -> 0.7007274 | G81: 0.729 | H81: =SUM(H82:H82) -> 0.484 | I81: =H81/G81 -> 0.66392318 | J81: =SUM(J82:J82) -> 0.533 | K81: =H81/C81 -> 1.2599573 | L81: =J81/C81 -> 1.387515 | M81: =J81/H81 -> 1.1012397
A82: Ingresospor ventas de bienes o servicios en MLC | B82: MMUSD | C82: 0.38414 | D82: =D74 -> 285.30412 | E82: =E74 -> 199.92042 | F82: =E82/D82 -> 0.7007274 | G82: 0.729 | H82: =H34 -> 0.484 | I82: =H82/G82 -> 0.66392318 | J82: =J34 -> 0.533 | K82: =H82/C82 -> 1.2599573 | L82: =J82/C82 -> 1.387515 | M82: =J82/H82 -> 1.1012397
A83: Importaciones de bienes y servicios | B83: MMUSD | C83: =SUM(C88+C96+C100) -> 0.00563 | D83: =SUM(D88+D96+D100) -> 0.428 | E83: =SUM(E88+E96+E100) -> 0.0053 | F83: =E83/D83 -> 0.012383178 | G83: =SUM(G88+G96+G100) -> 1.529 | H83: =SUM(H88+H96+H100) -> 1.209 | I83: =H83/G83 -> 0.79071288 | J83: =SUM(J88+J96+J100) -> 1.124 | K83: =H83/C83 -> 214.74245 | L83: =J83/C83 -> 199.64476 | M83: =J83/H83 -> 0.92969396
A84: Créditos externos comerciales | B84: MMUSD | F84: =E84/D84 -> #DIV/0! | I84: =H84/G84 -> #DIV/0! | K84: =H84/C84 -> #DIV/0! | L84: =J84/C84 -> #DIV/0! | M84: =J84/H84 -> #DIV/0!
A85: Corto plazo | B85: MMUSD | F85: =E85/D85 -> #DIV/0! | I85: =H85/G85 -> #DIV/0! | K85: =H85/C85 -> #DIV/0! | L85: =J85/C85 -> #DIV/0! | M85: =J85/H85 -> #DIV/0!
A86: Mediano Plazo | B86: MMUSD | F86: =E86/D86 -> #DIV/0! | I86: =H86/G86 -> #DIV/0! | K86: =H86/C86 -> #DIV/0! | L86: =J86/C86 -> #DIV/0! | M86: =J86/H86 -> #DIV/0!
A87: Largo Plazo | B87: MMUSD | F87: =E87/D87 -> #DIV/0! | I87: =H87/G87 -> #DIV/0! | K87: =H87/C87 -> #DIV/0! | L87: =J87/C87 -> #DIV/0! | M87: =J87/H87 -> #DIV/0!
A88: Créditos externos financieros | B88: MMUSD | C88: =SUM(C89:C91) -> 0 | D88: =SUM(D89:D91) -> 0.348 | E88: =SUM(E89:E91) -> 0 | F88: =E88/D88 -> 0 | G88: =SUM(G89:G91) -> 1.185 | H88: =SUM(H89:H91) -> 1.185 | I88: =H88/G88 -> 1 | J88: =SUM(J89:J91) -> 1.1 | K88: =H88/C88 -> #DIV/0! | L88: =J88/C88 -> #DIV/0! | M88: =J88/H88 -> 0.92827004
A89: Corto plazo | B89: MMUSD | C89: 0 | F89: =E89/D89 -> #DIV/0! | I89: =H89/G89 -> #DIV/0! | K89: =H89/C89 -> #DIV/0! | L89: =J89/C89 -> #DIV/0! | M89: =J89/H89 -> #DIV/0!
A90: Mediano Plazo | B90: MMUSD | C90: 0 | D90: 0.084 | F90: =E90/D90 -> 0 | G90: 0.3 | H90: 0.3 | I90: =H90/G90 -> 1 | J90: 0.3 | K90: =H90/C90 -> #DIV/0! | L90: =J90/C90 -> #DIV/0! | M90: =J90/H90 -> 1
A91: Largo Plazo | B91: MMUSD | D91: 0.264 | F91: =E91/D91 -> 0 | G91: 0.885 | H91: 0.885 | I91: =H91/G91 -> 1 | J91: 0.8 | K91: =H91/C91 -> #DIV/0! | L91: =J91/C91 -> #DIV/0! | M91: =J91/H91 -> 0.9039548
A92: Pago de deudas desde Cuba | B92: MMUSD | C92: =C94 -> 0.22893 | D92: =D94 -> 0 | E92: =E94 -> 0 | F92: =E92/D92 -> #DIV/0! | G92: =SUM(G93:G94) -> 0 | H92: =SUM(H93:H94) -> 2.364 | I92: =H92/G92 -> #DIV/0! | J92: =SUM(J93:J94) -> 2.35 | K92: =H92/C92 -> 10.326301 | L92: =J92/C92 -> 10.265147 | M92: =J92/H92 -> 0.99407783
A93: (+) Pago de Deudas con FP sin instrumentos bancarios | B93: MMUSD | F93: =E93/D93 -> #DIV/0! | I93: =H93/G93 -> #DIV/0! | K93: =H93/C93 -> #DIV/0! | L93: =J93/C93 -> #DIV/0! | M93: =J93/H93 -> #DIV/0!
A94: (-) Deudas que se pagan desde el exterior | B94: MMUSD | C94: 0.22893 | F94: =E94/D94 -> #DIV/0! | H94: 2.364 | I94: =H94/G94 -> #DIV/0! | J94: 2.35 | K94: =H94/C94 -> 10.326301 | L94: =J94/C94 -> 10.265147 | M94: =J94/H94 -> 0.99407783
A95: Pagos internos | B95: MMUSD | C95: =SUM(C96:C98) -> 0 | D95: =SUM(D96:D98) -> 0.16 | E95: =SUM(E96:E98) -> 0.044 | F95: =E95/D95 -> 0.275 | G95: =SUM(G96:G98) -> 0.64 | H95: =SUM(H96:H98) -> 5.63991 | I95: =H95/G95 -> 8.8123594 | J95: =SUM(J96:J98) -> 5.9 | K95: =H95/C95 -> #DIV/0! | L95: =J95/C95 -> #DIV/0! | M95: =J95/H95 -> 1.046116
A96: Pagos de Bienes y Servicios a entidades radicadas en la ZED Mariel | B96: MMUSD | D96: 0.08 | F96: =E96/D96 -> 0 | G96: 0.32 | H96: 0 | I96: =H96/G96 -> 0 | K96: =H96/C96 -> #DIV/0! | L96: =J96/C96 -> #DIV/0! | M96: =J96/H96 -> #DIV/0!
A97: Pagos de Bienes y Servicios a Empresas Mixtas | B97: MMUSD | D97: =G97/4 -> 0.08 | E97: 0.044 | F97: =E97/D97 -> 0.55 | G97: 0.32 | H97: 0.324 | I97: =H97/G97 -> 1.0125 | J97: 0.4 | K97: =H97/C97 -> #DIV/0! | L97: =J97/C97 -> #DIV/0! | M97: =J97/H97 -> 1.2345679
A98: Pagos de Bienes y Servicios a Entidades Estatales | B98: MMUSD | F98: =E98/D98 -> #DIV/0! | H98: 5.31591 | I98: =H98/G98 -> #DIV/0! | J98: 5.5 | K98: =H98/C98 -> #DIV/0! | L98: =J98/C98 -> #DIV/0! | M98: =J98/H98 -> 1.03463
A99: Demanda de compra de divisa | B99: MMUSD | C99: =SUM(C100:C101) -> 0.23456 | D99: =SUM(D100:D101) -> 0.348 | E99: =SUM(E100:E101) -> 0.0053 | F99: =E99/D99 -> 0.015229885 | G99: =SUM(G100:G101) -> 1.849 | H99: =SUM(H100:H101) -> 9.21291 | I99: =H99/G99 -> 4.9826447 | J99: =SUM(J100:J101) -> 9.374 | K99: =H99/C99 -> 39.277413 | L99: =J99/C99 -> 39.964188 | M99: =J99/H99 -> 1.0174852
A100: Gastos de Viajes | B100: MMUSD | C100: 0.00563 | E100: 0.0053 | F100: =E100/D100 -> #DIV/0! | G100: 0.024 | H100: 0.024 | I100: =H100/G100 -> 1 | J100: 0.024 | K100: =H100/C100 -> 4.2628774 | L100: =J100/C100 -> 4.2628774 | M100: =J100/H100 -> 1
A101: Demanda de compra de divisa por asignación semanal | B101: MMUSD | C101: =C92+C88 -> 0.22893 | D101: =D92+D88 -> 0.348 | E101: =E92+E88 -> 0 | F101: =E101/D101 -> 0 | G101: =G95+G92+G88 -> 1.825 | H101: =H95+H92+H88 -> 9.18891 | I101: =H101/G101 -> 5.0350192 | J101: =J95+J92+J88 -> 9.35 | K101: =H101/C101 -> 40.138514 | L101: =J101/C101 -> 40.842179 | M101: =J101/H101 -> 1.0175309
...

Sheet Modelo Indicadores Decreto 87
S1: R
A2: Unidad organizativa: OSDE Campismo Popular
A3: INDICADORES | B3: UM | C3: REAL EJERCICIO 2024 | D3: ACUMULADO | F3: Plan Anual 2025 | G3: Variación % | M3: Resumen de Indicadores Fundamentales | N3: Ministerio de Economía y Planificación | T3: Modelo: I-1
D4: Plan 2025 | E4: Real 2025 | G4: P 25 / R 24 Art.7.1 Decreto 87 | H4: Real 25/ Plan 25 Acum Art 8.1 Decreto 87 | N4: Plan 2023
A5: 1 | B5: 2 | D5: 8 | E5: 9 | F5: 5 | G5: 10 | H5: 11 | M5: Indicadores | N5: UM | O5: Real 2024 | P5: Año 2025 | R5: Plan 2025 | S5: Relaciones
A6: INGRESOS TOTALES | B6: MP | C6: =C28+C50+C72+C94+C116+C138+C160+C182+C204+C226+C248+C270+C292+C314+C336+C358 -> 1801610.3 | D6: =D28+D50+D72+D94+D116+D138+D160+D182+D204+D226+D248+D270+D292+D314+D336+D358 -> 794548.84 | E6: =E28+E50+E72+E94+E116+E138+E160+E182+E204+E226+E248+E270+E292+E314+E336+E358 -> 973208.86 | F6: 1844302.9 | G6: =F6/C6 -> 1.0236969 | H6: =E6/D6 -> 1.2248572 | P6: Plan | Q6: Real | S6: R25/P25 | T6: P25/R24
A7: VENTAS NETAS TOTALES | B7: MP | C7: =C29+C51+C73+C95+C117+C139+C161+C183+C205+C227+C249+C271+C293+C315+C337+C359 -> 1735074.2 | D7: =D29+D51+D73+D95+D117+D139+D161+D183+D205+D227+D249+D271+D293+D315+D337+D359 -> 774011.67 | E7: =E29+E51+E73+E95+E117+E139+E161+E183+E205+E227+E249+E271+E293+E315+E337+E359 -> 952633.89 | F7: 1796900 | G7: =F7/C7 -> 1.035633 | H7: =E7/D7 -> 1.2307746 | M7: SECTOR ESTATAL
A8: UTILIDAD ANTES DE IMPUESTO.5921-04 (Fila 40) | B8: MP | C8: =C30+C52+C74+C96+C118+C140+C162+C184+C206+C228+C250+C272+C294+C316+C338+C360 -> 131961.18 | D8: =D30+D52+D74+D96+D118+D140+D162+D184+D206+D228+D250+D272+D294+D316+D338+D360 -> 47177.315 | E8: =E30+E52+E74+E96+E118+E140+E162+E184+E206+E228+E250+E272+E294+E316+E338+E360 -> 90120.6 | F8: 155620 | G8: =F8/C8 -> 1.1792862 | H8: =E8/D8 -> 1.9102528 | M8: Ingresos Totales | N8: MP | O8: 1801610.3 | P8: 794548.84 | Q8: 973208.86 | R8: 1844302.9 | S8: =Q8/P8 -> 1.2248572 | T8: =R8/O8 -> 1.0236969
A9: APORTE POR EL RENDIMIENTO DE LA INVERSION ESTATAL O DIVIDENDOS | B9: MP | C9: =I13 -> 48891.617 | D9: =J13 -> 17479.195 | E9: =K13 -> 33389.682 | F9: =L13 -> 57657.21 | G9: =F9/C9 -> 1.1792862 | H9: =E9/D9 -> 1.9102528 | I9: =C8*5% -> 6598.059 | J9: =D8*5% -> 2358.8658 | K9: =E8*5% -> 4506.03 | L9: =F8*5% -> 7781 | M9: Costos y Gastos Totales | N9: MP | O9: =O8-O10 -> 1669649.2 | P9: =P8-P10 -> 747371.52 | Q9: =Q8-Q10 -> 883088.26 | R9: =R8-R10 -> 1688682.9 | S9: =Q9/P9 -> 1.1815921 | T9: =R9/O9 -> 1.0113998
A10: VALOR AGREGADO BRUTO | B10: MP | C10: =C32+C54+C76+C98+C120+C142+C164+C186+C208+C230+C252+C274+C296+C318+C340+C362 -> 519803.69 | D10: =D32+D54+D76+D98+D120+D142+D164+D186+D208+D230+D252+D274+D296+D318+D340+D362 -> 273020.07 | E10: =E32+E54+E76+E98+E120+E142+E164+E186+E208+E230+E252+E274+E296+E318+E340+E362 -> 287805.51 | F10: 613880 | G10: =F10/C10 -> 1.1809843 | H10: =E10/D10 -> 1.0541551 | I10: =C8-I9 -> 125363.12 | J10: =D8-J9 -> 44818.449 | K10: =E8-K9 -> 85614.57 | L10: =F8-L9 -> 147839 | M10: Utilidad antes del Impuesto | N10: MP | O10: 131961.18 | P10: 47177.315 | Q10: 90120.6 | R10: 155620 | S10: =Q10/P10 -> 1.9102528 | T10: =R10/O10 -> 1.1792862
A11: PRODUCTIVIDAD POR TRABAJADOR (en base a Valor Agregado) | B11: p | C11: =C10/C14*1000 -> 121194.61 | D11: =D10/D14*1000 -> 55155.57 | E11: =E10/E14*1000 -> 67307.182 | F11: =F10/F14*1000 -> 118053.85 | G11: =F11/C11 -> 0.97408495 | H11: =E11/D11 -> 1.2203152 | I11: =I10*35% -> 43877.092 | J11: =J10*35% -> 15686.457 | K11: =K10*35% -> 29965.099 | L11: =L10*35% -> 51743.65 | M11: Gasto total por peso de Ingreso total | N11: Peso | O11: =O9/O8 -> 0.92675376 | P11: =P9/P8 -> 0.94062377 | Q11: =Q9/Q8 -> 0.9073985 | R11: =R9/R8 -> 0.91562123 | S11: =Q11/P11 -> 0.96467741 | T11: =R11/O11 -> 0.98798761
A12: FONDO DE SALARIO TOTAL 5924-04 (04) | B12: MP | C12: =C34+C56+C78+C100+C122+C144+C166+C188+C210+C232+C254+C276+C298+C320+C342+C364 -> 161064.87 | D12: =D34+D56+D78+D100+D122+D144+D166+D188+D210+D232+D254+D276+D298+D320+D342+D364 -> 115460.33 | E12: =E34+E56+E78+E100+E122+E144+E166+E188+E210+E232+E254+E276+E298+E320+E342+E364 -> 73600.15 | F12: 189925.33 | G12: =F12/C12 -> 1.1791853 | H12: =E12/D12 -> 0.63744969 | I12: =I10-I11 -> 81486.029 | J12: =J10-J11 -> 29131.992 | K12: =K10-K11 -> 55649.47 | L12: =L10-L11 -> 96095.35 | M12: EMPLEO Y SALARIO
A13: DE ELLO: SALARIO ESCALA | B13: MP | C13: =C35+C57+C79+C101+C123+C145+C167+C189+C211+C233+C255+C277+C299+C321+C343+C365 -> 193737.24 | D13: =D35+D57+D79+D101+D123+D145+D167+D189+D211+D233+D255+D277+D299+D321+D343+D365 -> 102182.39 | E13: =E35+E57+E79+E101+E123+E145+E167+E189+E211+E233+E255+E277+E299+E321+E343+E365 -> 65136.133 | F13: =F35+F57+F79+F101+F123+F145+F167+F189+F211+F233+F255+F277+F299+F321+F343+F365 -> 184898.91 | G13: =F13/C13 -> 0.95437983 | H13: =E13/D13 -> 0.63744969 | I13: =I12*60% -> 48891.617 | J13: =J12*60% -> 17479.195 | K13: =K12*60% -> 33389.682 | L13: =L12*60% -> 57657.21 | M13: Gasto de Salario | N13: MP | O13: 161064.87 | P13: 115460.33 | Q13: 73600.15 | R13: 189925.33 | S13: =Q13/P13 -> 0.63744969 | T13: =R13/O13 -> 1.1791853
A14: PROMEDIO DE TRABAJADORES M 5202 ONEI | B14: U | C14: =C36+C58+C80+C102+C124+C146+C168+C190+C212+C234+C256+C278+C300+C322+C344+C366 -> 4289 | D14: =D36+D58+D80+D102+D124+D146+D168+D190+D212+D234+D256+D278+D300+D322+D344+D366 -> 4950 | E14: =E36+E58+E80+E102+E124+E146+E168+E190+E212+E234+E256+E278+E300+E322+E344+E366 -> 4276 | F14: 5200 | G14: =F14/C14 -> 1.2124038 | H14: =E14/D14 -> 0.86383838 | M14: Oficina Central | N14: MP | O14: 2189.45 | P14: 2027.2 | Q14: 1082.72 | R14: 5983.63 | S14: =Q14/P14 -> 0.53409629 | T14: =R14/O14 -> 2.7329375
A15: SALARIO MEDIO MENSUAL | B15: P | C15: =C12/C14*1000 -> 37553.012 | D15: =D12/D14*1000 -> 23325.319 | E15: =E12/E14*1000 -> 17212.383 | F15: =F12/F14/12*1000 -> 3043.6751 | G15: =F15/C15 -> 0.081050092 | H15: =E15/D15 -> 0.73792702 | M15: Promedio de Trabajadores | N15: Uno | O15: 4289 | P15: 4950 | Q15: 4276 | R15: 5200 | S15: =Q15/P15 -> 0.86383838 | T15: =R15/O15 -> 1.2124038
A16: INGRESO MEDIO MENSUAL | B16: P | C16: =C6*1000/C14 -> 420053.7 | D16: =D6*1000/D14 -> 160514.92 | E16: =E6*1000/E14 -> 227597.96 | F16: =F6*1000/F14/12 -> 29556.136 | G16: =F16/C16 -> 0.070362755 | H16: =E16/D16 -> 1.417924 | M16: Oficina Central | N16: Uno | O16: 48 | P16: 75 | Q16: 35 | R16: 75 | S16: =Q16/P16 -> 0.46666667 | T16: =R16/O16 -> 1.5625
A17: Correlación Salario Medio Productividad | B17: Coef. | G17: =G15/G11 -> 0.08320639 | H17: =H15/H11 -> 0.60470197 | M17: Salario Medio | N17: Pesos | O17: =O13*1000/12/O15 -> 3129.4177 | P17: =P13*1000/6/P15 -> 3887.5531 | Q17: =Q13*1000/6/Q15 -> 2868.7305 | R17: =R13*1000/12/R15 -> 3043.6751 | S17: =Q17/P17 -> 0.73792702 | T17: =R17/O17 -> 0.9726011
A18: CorrelaciónARIE Fondo de Salarios | B18: Coef. | G18: =G12/G9 -> 0.99991443 | H18: =H12/H9 -> 0.33369912 | M18: Oficina Central | N18: Pesos | O18: =O14*1000/12/O16 -> 3801.1285 | P18: =P14*1000/6/P16 -> 4504.8889 | Q18: =Q14*1000/6/Q16 -> 5155.8095 | R18: =R14*1000/12/R16 -> 6648.4778 | S18: =Q18/P18 -> 1.1444921 | T18: =R18/O18 -> 1.74908
A19: Gasto de Salario / Dividendos | B19: Coef. | C19: =C12/C9 -> 3.2943249 | D19: =D12/D9 -> 6.605586 | E19: =E12/E9 -> 2.2042782 | F19: =F12/F9 -> 3.294043 | M19: Valor Agregado Bruto | N19: MP | O19: 519803.69 | P19: 273020.07 | Q19: 287805.51 | R19: 613880 | S19: =Q19/P19 -> 1.0541551 | T19: =R19/O19 -> 1.1809843
A20: Gasto de Salario / Valor Agregado Bruto | B20: Coef. | C20: =C12/C10 -> 0.30985711 | D20: =D12/D10 -> 0.42290051 | E20: =E12/E10 -> 0.25572877 | F20: =F12/F10 -> 0.3093851 | M20: Productividad a partir del VAB | N20: pesos | O20: =O19*1000/12/O15 -> 10099.551 | P20: =P19*1000/6/P15 -> 9192.5949 | Q20: =Q19*1000/6/Q15 -> 11217.864 | R20: =R19*1000/12/R15 -> 9837.8206 | S20: =Q20/P20 -> 1.2203152 | T20: =R20/O20 -> 0.97408495
A21: Salario Pagado Sin Respaldo Productivo (Dividendos) | B21: MP | M21: Aporte al RIE o pago de dividendos a los socios | N21: MP | O21: 117062.2 | P21: 119675.2 | Q21: 667433.3 | R21: 3287806.9 | S21: 570.2 | T21: 492.6
A22: Salario Pagado Sin Respaldo Productivo (Productividad) | B22: MP | M22: Proporción Aporte al RIE o pago de dividendos a los socios contra Fondo de Salario | S22: 3.33 | T22: 3.16
M23: Correlación Salario Medio Productividad | S23: =S17/S20 -> 0.60470197 | T23: 0.5
A24: Unidad organizativa: Pinar del Río
A25: INDICADORES | B25: UM | C25: REAL EJERCICIO 2024 | D25: ACUMULADO | F25: Plan Anual 2025 | G25: Variación %
D26: Plan 2025 | E26: Real 2025 | G26: P 25 / R 24 Art.7.1 Decreto 87 | H26: Real 25/ Plan 25 Acum Art 8.1 Decreto 87
A27: 1 | B27: 2 | D27: 8 | E27: 9 | F27: 5 | G27: 10 | H27: 11
A28: INGRESOS TOTALES | B28: MP | C28: 142058.34 | D28: =[7]RESULTADO!C7 -> 76804.007 | E28: =[7]RESULTADO!D7 -> 89157.88 | F28: =SUM([7]PR!L9) -> 168645.47 | G28: =F28/C28 -> 1.1871564 | H28: =E28/D28 -> 1.1608493
A29: VENTAS NETAS TOTALES | B29: MP | C29: 140115.34 | D29: =[7]RESULTADO!P7 -> 76804.007 | E29: =[7]RESULTADO!Q7 -> 88920.32 | F29: =SUM([7]PR!L10) -> 168645.47 | G29: =F29/C29 -> 1.2036189 | H29: =E29/D29 -> 1.1577563
A30: UTILIDAD ANTES DE IMPUESTO.5921-04 (Fila 40) | B30: MP | C30: 3446.9 | D30: =[7]RESULTADO!L7 -> 1297.0249 | E30: =[7]RESULTADO!M7 -> 16163.36 | F30: =SUM([7]PR!L35) -> 3756.2 | G30: =F30/C30 -> 1.0897328 | H30: =E30/D30 -> 12.461874
A31: APORTE POR EL RENDIMIENTO DE LA INVERSION ESTATAL O DIVIDENDOS | B31: MP | C31: =I35 -> 1277.0765 | D31: =J35 -> 480.54771 | E31: =K35 -> 5988.5249 | F31: =L35 -> 1391.6721 | G31: =F31/C31 -> 1.0897328 | H31: =E31/D31 -> 12.461874 | I31: =C30*5% -> 172.345 | J31: =D30*5% -> 64.851243 | K31: =E30*5% -> 808.168 | L31: =F30*5% -> 187.81 | M31: 5% reserva para Contingencia
A32: VALOR AGREGADO BRUTO | B32: MP | C32: 40856.73 | D32: ='[7]EMPLEO Y SALARIO'!C7 -> 22403.66 | E32: ='[7]EMPLEO Y SALARIO'!D7 -> 32325.66 | F32: =[7]PR!L5 -> 43326.64 | G32: =F32/C32 -> 1.0604529 | H32: =E32/D32 -> 1.442874 | I32: =C30-I31 -> 3274.555 | J32: =D30-J31 -> 1232.1736 | K32: =E30-K31 -> 15355.192 | L32: =F30-L31 -> 3568.39 | M32: Utilidad antes de Impuesto
A33: PRODUCTIVIDAD POR TRABAJADOR (en base a Valor Agregado) | B33: p | C33: 9302.5342 | D33: ='[7]EMPLEO Y SALARIO'!I27 -> 9334.8585 | E33: ='[7]EMPLEO Y SALARIO'!J27 -> 14720.246 | F33: =F32/F36*1000 -> 108316.6 | G33: =F33/C33 -> 11.643773 | H33: =E33/D33 -> 1.5769115 | I33: =I32*35% -> 1146.0943 | J33: =J32*35% -> 431.26077 | K33: =K32*35% -> 5374.3172 | L33: =L32*35% -> 1248.9365 | M33: 35% Aporte por la Utilidad
A34: FONDO DE SALARIO TOTAL 5924-04 (04) | B34: MP | C34: 18435.78 | D34: ='[7]EMPLEO Y SALARIO'!I7 -> 11204.115 | E34: ='[7]EMPLEO Y SALARIO'!J7 -> 4957.56 | F34: ='[7]PR B'!L30 -> 19158.2 | G34: =F34/C34 -> 1.0391858 | H34: =E34/D34 -> 0.44247672 | I34: =I32-I33 -> 2128.4608 | J34: =J32-J33 -> 800.91285 | K34: =K32-K33 -> 9980.8748 | L34: =L32-L33 -> 2319.4535 | M34: Utilidad despues de Impuesto
A35: DE ELLO: SALARIO ESCALA | C35: 16597.29 | D35: =D34*88.5% -> 9915.6418 | E35: =E34*88.5% -> 4387.4406 | F35: =F34*88.5% -> 16955.007 | G35: =F35/C35 -> 1.0215527 | H35: =E35/D35 -> 0.44247672 | I35: =I34*60% -> 1277.0765 | J35: =J34*60% -> 480.54771 | K35: =K34*60% -> 5988.5249 | L35: =L34*60% -> 1391.6721 | M35: Aporte Rendimiento Inversion
A36: PROMEDIO DE TRABAJADORES M 5202 ONEI | B36: U | C36: 366 | D36: ='[7]EMPLEO Y SALARIO'!L7 -> 400 | E36: ='[7]EMPLEO Y SALARIO'!M7 -> 366 | F36: 400 | G36: =F36/C36 -> 1.0928962 | H36: =E36/D36 -> 0.915
A37: SALARIO MEDIO MENSUAL | B37: P | C37: 4197.582 | D37: ='[7]EMPLEO Y SALARIO'!F27 -> 4668.3812 | E37: ='[7]EMPLEO Y SALARIO'!G27 -> 2257.541 | F37: =F34/F36/12*1000 -> 3991.2917 | G37: =F37/C37 -> 0.95085497 | H37: =E37/D37 -> 0.48358111
A38: INGRESO MEDIO MENSUAL | B38: P | C38: 32344.795 | D38: =D28*1000/D36/2 -> 96005.008 | E38: =E28*1000/E36/2 -> 121800.38 | F38: =F28*1000/F36/12 -> 35134.473 | G38: =F38/C38 -> 1.0862481 | H38: =E38/D38 -> 1.2686878
A39: Correlación Salario Medio/ Productividad | B39: Coef. | G39: =G37/G33 -> 0.081662099 | H39: =H37/H33 -> 0.30666344
A40: CorrelaciónFondo de Salarios/ARIE | B40: Coef. | G40: =G34/G31 -> 0.95361519 | H40: =H34/H31 -> 0.035506436
A41: Gasto de Salario / Dividendos | B41: Coef. | C41: 5.3485103 | D41: =D34/D31 -> 23.315302 | E41: =E34/E31 -> 0.82784327 | F41: =F34/F31 -> 13.766318
A42: Gasto de Salario / Valor Agregado Bruto | B42: Coef. | C42: 7.2842422 | D42: =D34/D32 -> 0.50010198 | E42: =E34/E32 -> 0.15336299 | F42: =F34/F32 -> 0.44218061
A43: Salario Pagado Sin Respaldo Productivo (Dividendos) | B43: MP
A44: Salario Pagado Sin Respaldo Productivo (Productividad) | B44: MP
A46: Unidad organizativa: Artemisa
A47: INDICADORES | B47: UM | C47: REAL EJERCICIO 2024 | D47: ACUMULADO | F47: Plan Anual 2025 | G47: Variación %
D48: Plan 2025 | E48: Real 2025 | G48: P 25 / R 24 Art.7.1 Decreto 87 | H48: Real 25/ Plan 25 Acum Art 8.1 Decreto 87
A49: 1 | B49: 2 | D49: 8 | E49: 9 | F49: 5 | G49: 10 | H49: 11
A50: INGRESOS TOTALES | B50: MP | C50: 332136.93 | D50: =[7]RESULTADO!C8 -> 103854.91 | E50: =[7]RESULTADO!D8 -> 104685.92 | F50: =[7]ART!L9 -> 294471.3 | G50: =F50/C50 -> 0.88659608 | H50: =E50/D50 -> 1.0080016
A51: VENTAS NETAS TOTALES | B51: MP | C51: 331802.67 | D51: =[7]RESULTADO!P8 -> 103854.91 | E51: =[7]RESULTADO!Q8 -> 104660.52 | F51: =[7]ART!L10 -> 294471.3 | G51: =F51/C51 -> 0.88748924 | H51: =E51/D51 -> 1.0077571
A52: UTILIDAD ANTES DE IMPUESTO.5921-04 (Fila 40) | B52: MP | C52: 11579.53 | D52: =[7]RESULTADO!L8 -> 3254.7749 | E52: =[7]RESULTADO!M8 -> 2513.35 | F52: =[7]ART!L35 -> 14730.801 | G52: =F52/C52 -> 1.2721415 | H52: =E52/D52 -> 0.77220393
A53: APORTE POR EL RENDIMIENTO DE LA INVERSION ESTATAL O DIVIDENDOS | B53: MP | C53: =I57 -> 4290.2159 | D53: =J57 -> 1205.8941 | E53: =K57 -> 931.19617 | F53: =L57 -> 5457.7618 | G53: =F53/C53 -> 1.2721415 | H53: =E53/D53 -> 0.77220393 | I53: =C52*5% -> 578.9765 | J53: =D52*5% -> 162.73875 | K53: =E52*5% -> 125.6675 | L53: =F52*5% -> 736.54005
A54: VALOR AGREGADO BRUTO | B54: MP | C54: 70871.09 | D54: ='[7]EMPLEO Y SALARIO'!C8 -> 28080.942 | E54: ='[7]EMPLEO Y SALARIO'!D8 -> 23280.16 | F54: =[7]ART!L5+11500 -> 86045.852 | G54: =F54/C54 -> 1.2141178 | H54: =E54/D54 -> 0.82903771 | I54: =C52-I53 -> 11000.553 | J54: =D52-J53 -> 3092.0362 | K54: =E52-K53 -> 2387.6825 | L54: =F52-L53 -> 13994.261
A55: PRODUCTIVIDAD POR TRABAJADOR (en base a Valor Agregado) | B55: p | C55: 15749.131 | D55: ='[7]EMPLEO Y SALARIO'!I28 -> 9360.3141 | E55: ='[7]EMPLEO Y SALARIO'!J28 -> 10346.738 | F55: =F54/F58*1000/12 -> 13842.64 | G55: =F55/C55 -> 0.87894629 | H55: =E55/D55 -> 1.1053836 | I55: =I54*35% -> 3850.1937 | J55: =J54*35% -> 1082.2127 | K55: =K54*35% -> 835.68887 | L55: =L54*35% -> 4897.9913
A56: FONDO DE SALARIO TOTAL 5924-04 (04) | B56: MP | C56: 16582.15 | D56: ='[7]EMPLEO Y SALARIO'!I8 -> 9755.9 | E56: ='[7]EMPLEO Y SALARIO'!J8 -> 5962.61 | F56: ='[7]ART B '!L30 -> 20038.59 | G56: =F56/C56 -> 1.2084434 | H56: =E56/D56 -> 0.6111799 | I56: =I54-I55 -> 7150.3598 | J56: =J54-J55 -> 2009.8235 | K56: =K54-K55 -> 1551.9936 | L56: =L54-L55 -> 9096.2696
A57: DE ELLO: SALARIO ESCALA | B57: MP | C57: 14361.95 | D57: =D56*88.5% -> 8633.9715 | E57: =E56*88.5% -> 5276.9099 | F57: =F56*88.5% -> 17734.152 | G57: =F57/C57 -> 1.2348011 | H57: =E57/D57 -> 0.6111799 | I57: =I56*60% -> 4290.2159 | J57: =J56*60% -> 1205.8941 | K57: =K56*60% -> 931.19617 | L57: =L56*60% -> 5457.7618
A58: PROMEDIO DE TRABAJADORES M 5202 ONEI | B58: U | C58: 375 | D58: ='[7]EMPLEO Y SALARIO'!L8 -> 500 | E58: ='[7]EMPLEO Y SALARIO'!M8 -> 375 | F58: 518 | G58: =F58/C58 -> 1.3813333 | H58: =E58/D58 -> 0.75
A59: SALARIO MEDIO MENSUAL | B59: P | C59: 3684.9222 | D59: ='[7]EMPLEO Y SALARIO'!F28 -> 3251.9667 | E59: ='[7]EMPLEO Y SALARIO'!G28 -> 2650.0489 | F59: =F56/F58/12*1000 -> 3223.7114 | G59: =F59/C59 -> 0.87483838 | H59: =E59/D59 -> 0.81490654
A60: INGRESO MEDIO MENSUAL | B60: P | C60: 73808.207 | D60: =D50*1000/D58/2 -> 103854.91 | E60: =E50*1000/E58/2 -> 139581.23 | F60: =F50*1000/F58/12 -> 47373.118 | G60: =F60/C60 -> 0.64184079 | H60: =E60/D60 -> 1.3440022
A61: Correlación Salario Medio/ Productividad | B61: Coef. | G61: =G59/G55 -> 0.99532633 | H61: =H59/H55 -> 0.73721604
A62: CorrelaciónFondo de Salarios/ARIE | B62: Coef. | G62: =G56/G53 -> 0.94992844 | H62: =H56/H53 -> 0.79147474
A63: Gasto de Salario / ARIE | B63: Coef. | C63: 3.8651085 | D63: =D56/D53 -> 8.0901796 | E63: =E56/E53 -> 6.4031728 | F63: =F56/F53 -> 3.6715765
A64: Gasto de Salario / Valor Agregado Bruto | B64: Coef. | C64: 0.23397622 | D64: =D56/D54 -> 0.34742068 | E64: =E56/E54 -> 0.2561241 | F64: =F56/F54 -> 0.2328827
A65: Salario Pagado Sin Respaldo Productivo (ARIE) | B65: MP
A66: Salario Pagado Sin Respaldo Productivo (Productividad) | B66: MP
A68: Unidad organizativa: La Habana
A69: INDICADORES | B69: UM | C69: REAL EJERCICIO 2024 | D69: ACUMULADO | F69: Plan Anual 2025 | G69: Variación %
D70: Plan 2025 | E70: Real 2025 | G70: P 25 / R 24 Art.7.1 Decreto 87 | H70: Real 25/ Plan 25 Acum Art 8.1 Decreto 87
A71: 1 | B71: 2 | D71: 8 | E71: 9 | F71: 5 | G71: 10 | H71: 11
A72: INGRESOS TOTALES | B72: MP | C72: 197321.38 | D72: =[7]RESULTADO!C9 -> 76602.319 | E72: =[7]RESULTADO!D9 -> 111410.94 | F72: =[7]HAB!L9 -> 199990.01 | G72: =F72/C72 -> 1.0135243 | H72: =E72/D72 -> 1.4544069
A73: VENTAS NETAS TOTALES | B73: MP | C73: 196253.75 | D73: =[7]RESULTADO!P9 -> 76602.319 | E73: =[7]RESULTADO!Q9 -> 111046.73 | F73: =[7]HAB!L10 -> 199990.01 | G73: =F73/C73 -> 1.0190379 | H73: =E73/D73 -> 1.4496523
A74: UTILIDAD ANTES DE IMPUESTO.5921-04 (Fila 40) | B74: MP | C74: 19791.08 | D74: =[7]RESULTADO!L9 -> 4030.0477 | E74: =[7]RESULTADO!M9 -> 14020.67 | F74: =[7]HAB!L35 -> 19999 | G74: =F74/C74 -> 1.0105057 | H74: =E74/D74 -> 3.4790333
A75: APORTE POR EL RENDIMIENTO DE LA INVERSION ESTATAL O DIVIDENDOS | B75: MP | C75: =I79 -> 7332.5951 | D75: =J79 -> 1493.1327 | E75: =K79 -> 5194.6582 | F75: =L79 -> 7409.6295 | G75: =F75/C75 -> 1.0105057 | H75: =E75/D75 -> 3.4790333 | I75: =C74*5% -> 989.554 | J75: =D74*5% -> 201.50238 | K75: =E74*5% -> 701.0335 | L75: =F74*5% -> 999.95
A76: VALOR AGREGADO BRUTO | B76: MP | C76: 60319.78 | D76: ='[7]EMPLEO Y SALARIO'!C10 -> 22352.923 | E76: ='[7]EMPLEO Y SALARIO'!D10 -> 37554.97 | F76: =[7]HAB!L5 -> 64735.561 | G76: =F76/C76 -> 1.0732062 | H76: =E76/D76 -> 1.6800922 | I76: =C74-I75 -> 18801.526 | J76: =D74-J75 -> 3828.5453 | K76: =E74-K75 -> 13319.636 | L76: =F74-L75 -> 18999.05
A77: PRODUCTIVIDAD POR TRABAJADOR (en base a Valor Agregado) | B77: p | C77: 22241.807 | D77: ='[7]EMPLEO Y SALARIO'!I30 -> 22578.71 | E77: ='[7]EMPLEO Y SALARIO'!J30 -> 27695.406 | F77: =F76/F80*1000/12 -> 32694.728 | G77: =F77/C77 -> 1.4699673 | H77: =E77/D77 -> 1.226616 | I77: =I76*35% -> 6580.5341 | J77: =J76*35% -> 1339.9908 | K77: =K76*35% -> 4661.8728 | L77: =L76*35% -> 6649.6675
A78: FONDO DE SALARIO TOTAL 5924-04 (04) | B78: MP | C78: 15316.97 | D78: ='[7]EMPLEO Y SALARIO'!I10 -> 8300 | E78: ='[7]EMPLEO Y SALARIO'!J10 -> 7884.9 | F78: ='[7]HAB B'!L30-3700 -> 15400 | G78: =F78/C78 -> 1.0054208 | H78: =E78/D78 -> 0.94998795 | I78: =I76-I77 -> 12220.992 | J78: =J76-J77 -> 2488.5544 | K78: =K76-K77 -> 8657.7637 | L78: =L76-L77 -> 12349.383
A79: DE ELLO: SALARIO ESCALA | B79: MP | C79: 13433.41 | D79: =D78*88.5% -> 7345.5 | E79: =E78*88.5% -> 6978.1365 | F79: =F78*88.5% -> 13629 | G79: =F79/C79 -> 1.01456 | H79: =E79/D79 -> 0.94998795 | I79: =I78*60% -> 7332.5951 | J79: =J78*60% -> 1493.1327 | K79: =K78*60% -> 5194.6582 | L79: =L78*60% -> 7409.6295
A80: PROMEDIO DE TRABAJADORES M 5202 ONEI | B80: U | C80: 226 | D80: =[7]HAB!J56 -> 165 | E80: =[7]HAB!K56 -> 226 | F80: ='[7]EMPLEO Y SALARIO'!L10 -> 165 | G80: =F80/C80 -> 0.7300885 | H80: =E80/D80 -> 1.369697
A81: SALARIO MEDIO MENSUAL | B81: P | C81: 5647.8503 | D81: ='[7]EMPLEO Y SALARIO'!F30 -> 8383.8384 | E81: ='[7]EMPLEO Y SALARIO'!G30 -> 5814.823 | F81: =F78/12*1000/F80 -> 7777.7778 | G81: =F81/C81 -> 1.3771218 | H81: =E81/D81 -> 0.69357527
A82: INGRESO MEDIO MENSUAL | B82: P | C82: 72758.621 | D82: =D72*1000/D80/2 -> 232128.24 | E82: =E72*1000/E80/2 -> 246484.38 | F82: =F72*1000/12/F80 -> 101005.06 | G82: =F82/C82 -> 1.3882211 | H82: =E82/D82 -> 1.0618457
A83: Correlación Salario Medio/ Productividad | B83: Coef. | G83: =G81/G77 -> 0.93683842 | H83: =H81/H77 -> 0.565438
A84: CorrelaciónFondo de Salarios/ARIE | B84: Coef. | G84: =G78/G75 -> 0.99496791 | H84: =H78/H75 -> 0.2730609
A85: Gasto de Salario / Dividendos | B85: Coef. | C85: 2.088888 | D85: =D78/D75 -> 5.5587827 | E85: =E78/E75 -> 1.5178862 | F85: =F78/F75 -> 2.0783765
A86: Gasto de Salario / Valor Agregado Bruto | B86: Coef. | C86: 0.25392947 | D86: =D78/D76 -> 0.3713161 | E86: =E78/E76 -> 0.20995623 | F86: =F78/F76 -> 0.23789089
A87: Salario Pagado Sin Respaldo Productivo (ARIE) | B87: MP
A88: Salario Pagado Sin Respaldo Productivo (Productividad) | B88: MP
A90: Unidad organizativa: Casa Matríz
A91: INDICADORES | B91: UM | C91: REAL EJERCICIO 2024 | D91: ACUMULADO | F91: Plan Anual 2025 | G91: Variación %
D92: Plan 2025 | E92: Real 2025 | G92: P 25 / R 24 Art.7.1 Decreto 87 | H92: Real 25/ Plan 25 Acum Art 8.1 Decreto 87
A93: 1 | B93: 2 | D93: 8 | E93: 9 | F93: 5 | G93: 10 | H93: 11
A94: INGRESOS TOTALES | B94: MP | C94: 42217.86 | D94: =[7]OC!J9 -> 19635.283 | E94: =[7]OC!K9 -> 16945.77 | F94: =[7]OC!L9 -> 45584.13 | G94: =F94/C94 -> 1.0797357 | H94: =E94/D94 -> 0.86302653
A95: VENTAS NETAS TOTALES | B95: MP | G95: =F95/C95 -> #DIV/0! | H95: =E95/D95 -> #DIV/0!
A96: UTILIDAD ANTES DE IMPUESTO.5921-04 (Fila 40) | B96: MP | C96: 3951.13 | D96: =[7]OC!J35 -> -0.0066348686 | E96: =[7]OC!K35 -> 0 | F96: =[7]OC!L35 -> 0.0014953082 | G96: =F96/C96 -> 3.7845077e-07 | H96: =E96/D96 -> 0
A97: APORTE POR EL RENDIMIENTO DE LA INVERSION ESTATAL O DIVIDENDOS | B97: MP | G97: =F97/C97 -> #DIV/0! | H97: =E97/D97 -> #DIV/0! | I97: =C96*5% -> 197.5565 | J97: =D96*5% -> -0.00033174343 | K97: =E96*5% -> 0 | L97: =F96*5% -> 7.476541e-05
A98: VALOR AGREGADO BRUTO | B98: MP | C98: 6607.01 | D98: =[7]OC!J5 -> 2434.2514 | E98: =[7]OC!K5 -> 1463.71 | F98: =[7]OC!L5 -> 7192.9412 | G98: =F98/C98 -> 1.0886833 | H98: =E98/D98 -> 0.6012978 | I98: =C96-I97 -> 3753.5735 | J98: =D96-J97 -> -0.0063031251 | K98: =E96-K97 -> 0 | L98: =F96-L97 -> 0.0014205428
A99: PRODUCTIVIDAD POR TRABAJADOR (en base a Valor Agregado) | B99: p | C99: 11470.503 | D99: =D98/D102*1000 -> 32456.685 | E99: =E98/E102*1000 -> 41820.286 | F99: =F98/F102*1000 -> 95905.883 | G99: =F99/C99 -> 8.3610874 | H99: =E99/D99 -> 1.2884953 | I99: =I98*35% -> 1313.7507 | J99: =J98*35% -> -0.0022060938 | K99: =K98*35% -> 0 | L99: =L98*35% -> 0.00049718998
A100: FONDO DE SALARIO TOTAL 5924-04 (04) | B100: MP | C100: 2189.45 | D100: ='[7]OC B'!J30 -> 2027.2 | E100: ='[7]OC B'!K30 -> 1082.72 | F100: ='[7]OC B'!L30 -> 5983.63 | G100: =F100/C100 -> 2.7329375 | H100: =E100/D100 -> 0.53409629 | I100: =I98-I99 -> 2439.8228 | J100: =J98-J99 -> -0.0040970313 | K100: =K98-K99 -> 0 | L100: =L98-L99 -> 0.00092335282
A101: DE ELLO: SALARIO ESCALA | B101: MP | C101: 1891.02 | D101: =D100*88.5% -> 1794.072 | E101: =E100*88.5% -> 958.2072 | F101: =F100*88.5% -> 5295.5126 | G101: =F101/C101 -> 2.8003472 | H101: =E101/D101 -> 0.53409629 | I101: =I100*60% -> 1463.8937 | J101: =J100*60% -> -0.0024582188 | K101: =K100*60% -> 0 | L101: =L100*60% -> 0.00055401169
A102: PROMEDIO DE TRABAJADORES M 5202 ONEI | B102: U | C102: 48 | D102: =[7]OC!J56 -> 75 | E102: =[7]OC!K56 -> 35 | F102: ='[7]EMPLEO Y SALARIO'!L9 -> 75 | G102: =F102/C102 -> 1.5625 | H102: =E102/D102 -> 0.46666667
A103: SALARIO MEDIO MENSUAL | B103: P | C103: 3801.1285 | D103: =D100/D102*1000 -> 27029.333 | E103: =E100/E102*1000 -> 30934.857 | F103: =F100/F102/12*1000 -> 6648.4778 | G103: =F103/C103 -> 1.74908 | H103: =E103/D103 -> 1.1444921
...
